src/modules/data_memory.v
// data_memory.v

module data_memory #(
  parameter DATA_WIDTH = 32, MEM_ADDR_SIZE = 8
)(
  input  clk,
  input  mem_write,
  input  mem_read,
  input  [1:0] maskmode,
  input  sext,
  input  [DATA_WIDTH-1:0] address,
  input  [DATA_WIDTH-1:0] write_data,

  output reg [DATA_WIDTH-1:0] read_data
);

  // memory
  reg [DATA_WIDTH-1:0] mem_array [0:2**MEM_ADDR_SIZE-1]; // change memory size
  initial $readmemh("data/data_memory.mem", mem_array);
  // wire reg for writedata
  wire [MEM_ADDR_SIZE-1:0] address_internal; // 256 = 8-bit address

  assign address_internal = address[MEM_ADDR_SIZE+1:2]; // 256 = 8-bit address

  // update at negative edge
  always @(negedge clk) begin 
    if (mem_write == 1'b1) begin
      ////////////////////////////////////////////////////////////////////////
      // TODO : Perform writes (select certain bits from write_data
      // according to maskmode
      ////////////////////////////////////////////////////////////////////////
		case (maskmode)
			// store byte (1B)
			2'b00: mem_array[address_internal][7:0] = write_data[7:0];
			// store half-word (2B)
			2'b01: mem_array[address_internal][15:0] = write_data[15:0];
			// store word (4B)
			2'b10: mem_array[address_internal][31:0] = write_data[31:0];
		endcase	
	// TODO END
    end
  end

  // combinational logic
  always @(*) begin
    if (mem_read == 1'b1) begin
      ////////////////////////////////////////////////////////////////////////
      // TODO : Perform reads (select bits according to sext & maskmode)
      ////////////////////////////////////////////////////////////////////////
		case ({sext, maskmode})
			// load byte
			3'b0_00: read_data = {{24{mem_array[address_internal][7]}}, mem_array[address_internal][7:0]};
			// load half-word
			3'b0_01: read_data = {{16{mem_array[address_internal][15]}}, mem_array[address_internal][15:0]};
			// load word
			3'b0_10: read_data = mem_array[address_internal];
			// load byte Unsigned
			3'b1_00: read_data = {{24{1'b0}}, mem_array[address_internal][7:0]};
			// load half-word Unsigned
			3'b1_01: read_data = {{16{1'b0}}, mem_array[address_internal][15:0]};
		endcase
		// TODO END
    end else begin
      read_data = 32'h0000_0000;
    end
  end

endmodule

src/modules/mux_2x1.v
module mux_2x1
#(parameter DATA_WIDTH = 32)(
  input select,
  input [DATA_WIDTH-1:0] in1,
  input [DATA_WIDTH-1:0] in2,
  
  output reg [DATA_WIDTH-1:0] out
);

// combinational logic
always @ (*) begin
  case(select)
    1'b0: out = in1;
    1'b1: out = in2;
    default: out = {DATA_WIDTH{1'b0}}; // should never fall here
  endcase
end

endmodule

src/modules/branch_control.v
module branch_control
(
  // current pc
  input branch,
  input check,

  output reg taken 
);

///////////////////////////////////////////////////////////////////////////////
// TODO : You need to do something!
//////////////////////////////////////////////////////////////////////////////
always @(*) begin
	taken = branch & check;
end

endmodule

src/modules/defines.v
`ifndef __defines_vh__
`define __defines_vh__

// ALU function
`define OP_ADD  4'b0000
`define OP_SUB  4'b0001
`define OP_XOR  4'b0010
`define OP_OR   4'b0011
`define OP_AND  4'b0100
`define OP_SLL  4'b0101
`define OP_SRL  4'b0110
`define OP_SRA  4'b0111
`define OP_SLT  4'b1000
`define OP_SLTU 4'b1001
`define OP_BGE   4'b1010
`define OP_BGEU   4'b1011

`define OP_EEE  4'b1111   // error

`endif // __defines_vh__

src/modules/ALU.v
// ALU.v

// This module performs ALU operations according to the "alu_func" value,
// which is generated by the ALU control unit.
// Note that there exist 10 R-type instructions in RV32I:
// add, sub, xor, or, and, sll, srl, sra, slt, sltu

`include "defines.v"

module ALU 
#(parameter DATA_WIDTH = 32)(
  input [DATA_WIDTH-1:0] in_a, 
  input [DATA_WIDTH-1:0] in_b,
  input [3:0] alu_func,

  output reg [DATA_WIDTH-1:0] result,
  output reg check 
);

// combinational logic 
always @(*) begin
  case (alu_func)
    `OP_ADD:  result = in_a +  in_b; 
    `OP_SUB:  result = in_a -  in_b;
    `OP_XOR:  result = in_a ^  in_b;
    `OP_OR:   result = in_a |  in_b;
    `OP_AND:  result = in_a &  in_b;
    /////////////////////////////////////////////////////////////////////////
    // TODO : Add other operations
    // - The example below is given as a hint
    // - `OP_SRA: result = $signed(in_a) >>> in_b[4:0];
    /////////////////////////////////////////////////////////////////////////
	`OP_SLL: result = in_a << in_b[4:0];
    `OP_SRL: result = in_a >> in_b[4:0];
    `OP_SRA: result = $signed(in_a) >>> in_b[4:0];
    `OP_SLT: result = ($signed(in_a) < $signed(in_b)) ? 1:0;
    `OP_SLTU: result = (in_a < in_b) ? 1:0;
	// TODO END
    default:  result = 32'h0000_0000;
  endcase
end

// combinational logic
always @(*) begin
  case (alu_func)
    //////////////////////////////////////////////////////////////////////////
    // TODO : Generate check signal
    //////////////////////////////////////////////////////////////////////////
    `OP_SUB: check = (in_a - in_b == 0) ? 1:0;
	// TODO END
	default:  check = 1'b0;
  endcase
end
endmodule

src/modules/ALU_control.v
// ALU_control.v

/* This unit generates a 4-bit ALU control input (alu_func)
 * based on the 2-bit ALUOp control, funct7, and funct3 field.
 *
 * ALUOp | ALU action | notes  
 * ------|------------|---------------------
 *   00  | add        | for loads and stores
 *   01  | subtract   | for branches
 *   10  | it varies  | for R-types
 *   11  | it varies  | immediate
 *
 * R-type instructions (opcode: 0110011)
 * Name | funct3 | funct7
 * -----------------------
 * add  |  0x0   | 0x00
 * sub  |  0x0   | 0x20
 * xor  |  0x4   | 0x00
 * or   |  0x6   | 0x00
 * and  |  0x7   | 0x00
 * sll  |  0x1   | 0x00
 * srl  |  0x5   | 0x00
 * sra  |  0x5   | 0x20
 * slt  |  0x2   | 0x00
 * sltu |  0x3   | 0x00
 */

`include "defines.v"

module ALU_control(
  input wire [1:0] alu_op,
  input wire [6:0] funct7,
  input wire [2:0] funct3,

  output reg [3:0] alu_func
);

wire [3:0] funct;
assign funct = {funct7[5], funct3};

// combinational logic
always @(*) begin
  case (alu_op)
    2'b00: begin
    ///////////////////////////////////////////////////////////////////////
    // TODO : select operation for loads/stores
    ///////////////////////////////////////////////////////////////////////
		alu_func = `OP_ADD;
	//TODO END
    end
    2'b01: begin
    ///////////////////////////////////////////////////////////////////////
    // TODO : select operation for branches
    ///////////////////////////////////////////////////////////////////////
		alu_func = `OP_SUB;
	// TODO END
    end
    2'b10: begin                // R-types
      case (funct)
        4'b0_000: alu_func = `OP_ADD;
        4'b1_000: alu_func = `OP_SUB;
        4'b0_100: alu_func = `OP_XOR;
        4'b0_110: alu_func = `OP_OR;
        4'b0_111: alu_func = `OP_AND;
        4'b0_001: alu_func = `OP_SLL;
        4'b0_101: alu_func = `OP_SRL;
        4'b1_101: alu_func = `OP_SRA;
        4'b0_010: alu_func = `OP_SLT;
        4'b0_011: alu_func = `OP_SLTU;
        default:  alu_func = `OP_EEE;  // shoud not fall here 
      endcase
    end
    2'b11: begin
      ///////////////////////////////////////////////////////////////////////
      // TODO : select operation for I-types with immediate
      ///////////////////////////////////////////////////////////////////////
	casex (funct)
		4'bx_000: alu_func = `OP_ADD;
		4'bx_100: alu_func = `OP_XOR;
		4'bx_110: alu_func = `OP_OR;
		4'bx_111: alu_func = `OP_AND;
		4'b0_001: alu_func = `OP_SLL;
		4'b0_101: alu_func = `OP_SRL;
		4'b1_101: alu_func = `OP_SRA;
		4'bx_010: alu_func = `OP_SLT;
		4'bx_011: alu_func = `OP_SLTU;
		default: alu_func = `OP_EEE;
	endcase
    end
    default: alu_func = `OP_EEE;       // should not fall here
  endcase
end

endmodule

src/modules/imm_generator.v
// imm_generator.v

module imm_generator #(
  parameter DATA_WIDTH = 32
)(
  input [31:0] instruction,

  output reg [DATA_WIDTH-1:0] sextimm
);

wire [6:0] opcode;
assign opcode = instruction[6:0];

always @(*) begin
  case (opcode)
    //////////////////////////////////////////////////////////////////////////
    // TODO : Generate sextimm using instruction
    //////////////////////////////////////////////////////////////////////////
	// immediate Arithmetic (I-type)
	7'b001_0011: sextimm = {{20{instruction[31]}}, instruction[31:20]};
	// Load (I-type)
	7'b000_0011: sextimm = {{20{instruction[31]}}, instruction[31:20]};
	//Store (S-type)
    7'b010_0011: sextimm = {{20{instruction[31]}}, instruction[31:25], instruction[11:7]};
	//Branch (B-type)
	7'b110_0011: sextimm = {{19{instruction[31]}}, instruction[31], instruction[7], instruction[30:25], instruction[11:8], 1'b0};
	// Jump and Link (J-type)
	7'b110_1111: sextimm = {{11{instruction[31]}}, instruction[31], instruction[19:12], instruction[20], instruction[30:21], 1'b0};
	// Jump and Link Reg (I-type)
	7'b110_0111: sextimm = {{20{instruction[31]}}, instruction[31:20]};
	
	// TODO END
	
	default:     sextimm = 32'h0000_0000;
  endcase
end


endmodule

src/modules/register_file.v
// register_file.v
// this models 32, 32-bit registers

module register_file #(
  parameter DATA_WIDTH = 32,
  parameter ADDR_WIDTH = 5
)(
  input clk, 
  input  [ADDR_WIDTH-1:0] rs1, 
  input  [ADDR_WIDTH-1:0] rs2, 
  input  [ADDR_WIDTH-1:0] rd,
  input reg_write, 
  input  [DATA_WIDTH-1:0] write_data,

  output [DATA_WIDTH-1:0] rs1_out,
  output [DATA_WIDTH-1:0] rs2_out
);

  // memory array
  reg [DATA_WIDTH-1:0] reg_array[0:2**ADDR_WIDTH-1];
  initial $readmemh("data/register.mem", reg_array); // change initial register file for fib example

  // update regfile at the falling edge
  always @(negedge clk) begin 
    if (reg_write == 1'b1) reg_array[rd] <= write_data;
    reg_array[0] <= 0; // x0 is always zero in RISC-V
  end

  assign rs1_out = reg_array[rs1];
  assign rs2_out = reg_array[rs2];

endmodule

src/modules/control.v
// control.v

// The main control module takes as input the opcode field of an instruction
// (i.e., instruction[6:0]) and generates a set of control signals.

module control(
  input [6:0] opcode,

  output [1:0] jump,
  output branch,
  output mem_read,
  output mem_to_reg,
  output [1:0] alu_op,
  output mem_write,
  output alu_src,
  output reg_write
);

reg [9:0] controls;

// combinational logic
always @(*) begin
  case (opcode)
    7'b0110011: controls = 10'b00_000_10_001; // R-type
     
    //////////////////////////////////////////////////////////////////////////
    // TODO : Implement signals for other instruction types
    //////////////////////////////////////////////////////////////////////////
	7'b0010011: controls = 10'b00_000_11_011;//I-type
	7'b0000011: controls = 10'b00_011_00_011;//Load (I)
	7'b0100011: controls = 10'b00_00x_00_110;//Store (S)
	7'b1100011: controls = 10'b00_10x_01_000;//B-type
	7'b1101111: controls = 10'b01_00x_xx_0x1;//JAL (J)
	7'b1100111: controls = 10'b10_00x_xx_0x1;//JALR (I)
	// TODO END
    default:    controls = 10'b00_000_00_000;
  endcase
end

assign {jump, branch, mem_read, mem_to_reg, alu_op, mem_write, alu_src, reg_write} = controls;

endmodule

src/modules/adder.v
module adder #(
  parameter DATA_WIDTH = 32
)(
  input [DATA_WIDTH-1:0] in_a,
  input [DATA_WIDTH-1:0] in_b,

  output reg [DATA_WIDTH-1:0] result
);

// combinational logic
always @(*) begin
  result = in_a + in_b;
end

endmodule

src/simple_cpu.v
// simple_cpu.v
// a single-cycle RISC-V microarchitecture (RV32I)

module simple_cpu
#(parameter DATA_WIDTH = 32)(
  input clk,
  input rstn
);


////////////////////////////////////////////////////
// Instruction Fetch (IF)
////////////////////////////////////////////////////


/* m_next_pc_adder */
wire [DATA_WIDTH-1:0] PC_PLUS_4;
reg [DATA_WIDTH-1:0] PC;    // program counter (32 bits)

adder m_next_pc_adder(
  .in_a(PC),
  .in_b(32'h0000_0004),

  .result(PC_PLUS_4)
);

/* pc: update program counter */
wire [DATA_WIDTH-1:0] NEXT_PC;

always @(posedge clk) begin
  if (rstn == 1'b0) PC <= 32'h00000000;
  else PC <= NEXT_PC;
end


/* inst_memory: memory where instruction lies */
localparam NUM_INSTS = 64;

reg [31:0] inst_memory[0:NUM_INSTS-1];
initial $readmemb("data/inst.mem", inst_memory);


/* instruction: current instruction */
wire [DATA_WIDTH-1:0] instruction;
assign instruction = inst_memory[PC[7:2]]; // 64 inst


////////////////////////////////////////////////////
// Instruction Decode (ID)
////////////////////////////////////////////////////


// from register file 
wire [31:0] rs1_out, rs2_out;
wire [31:0] alu_out;

// 5 bits for each (because there exist 32 registers)
wire [4:0] rs1, rs2, rd;

wire [6:0] opcode;
wire [6:0] funct7;
wire [2:0] funct3;

// instruction fields
assign opcode = instruction[6:0];

assign funct7 = instruction[31:25];
assign funct3 = instruction[14:12];

// R type
assign rs1 = instruction[19:15];
assign rs2 = instruction[24:20];
assign rd  = instruction[11:7];

/* m_control: control unit */
wire branch;
wire mem_read;
wire mem_to_reg;
wire [1:0] alu_op;
wire mem_write;
wire alu_src;
wire reg_write;
wire [1:0] jump;

control m_control(
  .opcode(opcode),

  .jump(jump),
  .branch(branch),
  .mem_read(mem_read),
  .mem_to_reg(mem_to_reg),
  .alu_op(alu_op),
  .mem_write(mem_write),
  .alu_src(alu_src),
  .reg_write(reg_write)
);

/* m_register_file: register file */
wire [DATA_WIDTH-1:0] write_data; 
wire [DATA_WIDTH-1:0] read_data;
wire [31:0] immediate;

register_file m_register_file(
  .clk(clk),
  .rs1(rs1),
  .rs2(rs2),
  .rd(rd),
  .reg_write(reg_write),
  .write_data(write_data),
  
  .rs1_out(rs1_out),
  .rs2_out(rs2_out)
);

///////////////////////////////////////////////////////////////////////////////
// TODO : Immediate Generator
//////////////////////////////////////////////////////////////////////////////
//wire [31:0] immediate;

imm_generator imm_generator(
	.instruction(instruction),
	
	.sextimm(immediate)
);

////////////////////////////////////////////////////
// Execute (EX) 
////////////////////////////////////////////////////


/* m_ALU_control: ALU control unit */
wire [3:0] alu_func;

ALU_control m_ALU_control(
  .alu_op(alu_op), 
  .funct7(funct7),
  .funct3(funct3),

  .alu_func(alu_func)
);

wire [31:0] alu_in2;

///////////////////////////////////////////////////////////////////////////////
// TODO : Need a fix
//////////////////////////////////////////////////////////////////////////////
/*mux_2x1 mux_ALUSrc(
	.select(alu_src),
	.in1(rs2_out),
	.in2(immediate),
	
	.out(alu_in2)
);*/
 assign alu_in2 = (alu_src == 0) ? rs2_out:immediate;
// TODO END
//////////////////////////////////////////////////////////////////////////////

/* m_ALU: ALU */
wire [31:0] alu_in1;
wire alu_check;

assign alu_in1 = rs1_out;

ALU m_ALU(
  .in_a(alu_in1), 
  .in_b(alu_in2), // is input with reg allowed?? 
  .alu_func(alu_func),

  // output
  .result(alu_out),
  .check(alu_check)
);


////////////////////////////////////////////////////
// Memory (MEM) 
////////////////////////////////////////////////////

/* m_branch_control: generate taken for branch instruction */
wire taken;

branch_control m_branch_control(
  .branch(branch),
  .check(alu_check),

  .taken(taken)
);

///////////////////////////////////////////////////////////////////////////////
// TODO : Currently, NEXT_PC is always PC_PLUS_4. Using adders and muxes & 
// control signals, compute & assign the correct NEXT_PC.
//////////////////////////////////////////////////////////////////////////////
wire [31:0] PC_target;
mux_2x1 mux_PC(
	.select(taken),
	.in1(PC_PLUS_4),
	.in2(PC_target),

	.out(NEXT_PC)
);
// TODO END
//assign NEXT_PC = PC_PLUS_4;


///////////////////////////////////////////////////////////////////////////////
// TODO : Feed the appropriate inputs to the data memory
//////////////////////////////////////////////////////////////////////////////
/* m_data_memory: data memory */

data_memory m_data_memory(
  .clk(clk),
  .mem_write(mem_write),
  .mem_read(mem_read),
  .maskmode(funct3[1:0]),
  .sext(funct3[2]),
  .address(alu_out),
  .write_data(rs2_out),

  .read_data(read_data)
);
// TODO END
//////////////////////////////////////////////////////////////////////////////


////////////////////////////////////////////////////
// Write Back (WB) 
////////////////////////////////////////////////////

///////////////////////////////////////////////////////////////////////////////
// TODO : Need a fix
//////////////////////////////////////////////////////////////////////////////
assign write_data = (mem_to_reg == 0) ? alu_out:read_data;
// TODO END

//////////////////////////////////////////////////////////////////////////////
endmodule

src/riscv_tb.v
`timescale 1 ns/10 ps

module riscv_tb;

reg clk, rstn;
wire [31:0] inst;

integer i;

initial begin
  clk  = 1'b0;
  rstn = 1'b0;
  $display($time, " ** Start Simulation **");
  $display($time, " Instruction Memory ");
  for (i=0;i<64;i=i+1) $display($time, " INST[%2d]: %b", i, my_cpu.inst_memory[i]);
  $monitor($time, " [PC] pc : %d", my_cpu.PC);
  #60 rstn = 1'b1;
  #3760; // for Fibonacci example
  rstn = 1'b0;
  $display($time, " ** End Simulation **");
  $display($time, " REGISTER FILE");
  for (i=0;i<32;i=i+1) $display($time, " Reg[%d]: %d (%b)", i, $signed(my_cpu.m_register_file.reg_array[i]), my_cpu.m_register_file.reg_array[i]);
  $display($time, " DATA MEMORY");
  for (i=0;i<128;i=i+1) $display($time, " Mem[%d]: %d (%b)", i, $signed(my_cpu.m_data_memory.mem_array[i]), my_cpu.m_data_memory.mem_array[i]);
  $finish;
end

always begin
  #20 clk = ~clk;
end

// dump the state of the design
// VCD (Value Change Dump) is a standard dump format defined in Verilog.
initial begin
  $dumpfile("sim.vcd");
  $dumpvars(0, riscv_tb);
end

simple_cpu my_cpu(.clk(clk), .rstn(rstn));

endmodule

sim.vcd
$date
	Mon Apr  4 16:27:42 2022
$end
$version
	Icarus Verilog
$end
$timescale
	10ps
$end
$scope module riscv_tb $end
$var reg 1 ! clk $end
$var reg 1 " rstn $end
$var integer 32 # i [31:0] $end
$scope module my_cpu $end
$var wire 32 $ PC_target [31:0] $end
$var wire 32 % alu_in1 [31:0] $end
$var wire 1 ! clk $end
$var wire 32 & instruction [31:0] $end
$var wire 1 " rstn $end
$var wire 32 ' write_data [31:0] $end
$var wire 1 ( taken $end
$var wire 32 ) rs2_out [31:0] $end
$var wire 5 * rs2 [4:0] $end
$var wire 32 + rs1_out [31:0] $end
$var wire 5 , rs1 [4:0] $end
$var wire 1 - reg_write $end
$var wire 32 . read_data [31:0] $end
$var wire 5 / rd [4:0] $end
$var wire 7 0 opcode [6:0] $end
$var wire 1 1 mem_write $end
$var wire 1 2 mem_to_reg $end
$var wire 1 3 mem_read $end
$var wire 2 4 jump [1:0] $end
$var wire 32 5 immediate [31:0] $end
$var wire 7 6 funct7 [6:0] $end
$var wire 3 7 funct3 [2:0] $end
$var wire 1 8 branch $end
$var wire 1 9 alu_src $end
$var wire 32 : alu_out [31:0] $end
$var wire 2 ; alu_op [1:0] $end
$var wire 32 < alu_in2 [31:0] $end
$var wire 4 = alu_func [3:0] $end
$var wire 1 > alu_check $end
$var wire 32 ? PC_PLUS_4 [31:0] $end
$var wire 32 @ NEXT_PC [31:0] $end
$var reg 32 A PC [31:0] $end
$scope module imm_generator $end
$var wire 32 B instruction [31:0] $end
$var wire 7 C opcode [6:0] $end
$var reg 32 D sextimm [31:0] $end
$upscope $end
$scope module m_ALU $end
$var wire 32 E in_a [31:0] $end
$var wire 32 F in_b [31:0] $end
$var wire 4 G alu_func [3:0] $end
$var reg 1 > check $end
$var reg 32 H result [31:0] $end
$upscope $end
$scope module m_ALU_control $end
$var wire 3 I funct3 [2:0] $end
$var wire 7 J funct7 [6:0] $end
$var wire 4 K funct [3:0] $end
$var wire 2 L alu_op [1:0] $end
$var reg 4 M alu_func [3:0] $end
$upscope $end
$scope module m_branch_control $end
$var wire 1 > check $end
$var wire 1 8 branch $end
$var reg 1 ( taken $end
$upscope $end
$scope module m_control $end
$var wire 7 N opcode [6:0] $end
$var wire 1 - reg_write $end
$var wire 1 1 mem_write $end
$var wire 1 2 mem_to_reg $end
$var wire 1 3 mem_read $end
$var wire 2 O jump [1:0] $end
$var wire 1 8 branch $end
$var wire 1 9 alu_src $end
$var wire 2 P alu_op [1:0] $end
$var reg 10 Q controls [9:0] $end
$upscope $end
$scope module m_data_memory $end
$var wire 32 R address [31:0] $end
$var wire 1 ! clk $end
$var wire 2 S maskmode [1:0] $end
$var wire 1 3 mem_read $end
$var wire 1 1 mem_write $end
$var wire 1 T sext $end
$var wire 32 U write_data [31:0] $end
$var wire 8 V address_internal [7:0] $end
$var reg 32 W read_data [31:0] $end
$upscope $end
$scope module m_next_pc_adder $end
$var wire 32 X in_a [31:0] $end
$var wire 32 Y in_b [31:0] $end
$var reg 32 Z result [31:0] $end
$upscope $end
$scope module m_register_file $end
$var wire 1 ! clk $end
$var wire 5 [ rd [4:0] $end
$var wire 1 - reg_write $end
$var wire 5 \ rs1 [4:0] $end
$var wire 32 ] rs1_out [31:0] $end
$var wire 5 ^ rs2 [4:0] $end
$var wire 32 _ rs2_out [31:0] $end
$var wire 32 ` write_data [31:0] $end
$upscope $end
$scope module mux_PC $end
$var wire 32 a in1 [31:0] $end
$var wire 32 b in2 [31:0] $end
$var wire 1 ( select $end
$var reg 32 c out [31:0] $end
$upscope $end
$upscope $end
$upscope $end
$enddefinitions $end
#0
$dumpvars
b0 c
bz b
bx a
bx `
bx _
bx ^
bx ]
bx \
bx [
bx Z
b100 Y
bx X
b0 W
bx V
bx U
xT
bx S
bx R
bx Q
bx P
bx O
bx N
bx M
bx L
bx K
bx J
bx I
bx H
bx G
bx F
bx E
bx D
bx C
bx B
bx A
b0 @
bx ?
x>
bx =
bx <
bx ;
bx :
x9
x8
bx 7
bx 6
bx 5
bx 4
x3
x2
x1
bx 0
bx /
b0 .
x-
bx ,
bx +
bx *
bx )
x(
bx '
bx &
bx %
bz $
b1000000 #
0"
0!
$end
#2000
b100 @
b100 c
b0 4
b0 O
08
03
02
b11 ;
b11 L
b11 P
01
19
1-
0(
b111000 V
b11100000 '
b11100000 `
b11011 Q
b0 S
0T
b0 =
b0 G
b0 M
0>
b11100000 :
b11100000 H
b11100000 R
b11111111111111111111111111100000 <
b11111111111111111111111111100000 F
b10011 0
b10011 N
b1111111 6
b1111111 J
b1000 K
b0 7
b0 I
b100000000 %
b100000000 E
b100000000 +
b100000000 ]
b10 ,
b10 \
b0 )
b0 U
b0 _
b0 *
b0 ^
b10 /
b10 [
b11111111111111111111111111100000 5
b11111111111111111111111111100000 D
b10011 C
b11111110000000010000000100010011 &
b11111110000000010000000100010011 B
b100 ?
b100 Z
b100 a
b0 A
b0 X
1!
#4000
b110000 V
b11000000 '
b11000000 `
b11000000 :
b11000000 H
b11000000 R
b11100000 %
b11100000 E
b11100000 +
b11100000 ]
0!
#6000
b111111 V
b0xxxxxx00 '
b0xxxxxx00 `
x2
b0 ;
b0 L
b0 P
11
0-
b11111100 :
b11111100 H
b11111100 R
b0x00110 Q
b10 S
b0 =
b0 G
b0 M
b11100 <
b11100 F
b100011 0
b100011 N
b0 6
b0 J
b10 K
b10 7
b10 I
b1000 *
b1000 ^
b11100 /
b11100 [
b11100 5
b11100 D
b100011 C
b1000 @
b1000 c
b100000010010111000100011 &
b100000010010111000100011 B
b1000 ?
b1000 Z
b1000 a
b100 A
b100 X
1!
1"
#8000
0!
#10000
b111110 V
b0xxxxx000 '
b0xxxxx000 `
b11111000 :
b11111000 H
b11111000 R
b11000 <
b11000 F
b11011000 )
b11011000 U
b11011000 _
b1 *
b1 ^
b11000 /
b11000 [
b11000 5
b11000 D
b1100 @
b1100 c
b100010010110000100011 &
b100010010110000100011 B
b1100 ?
b1100 Z
b1100 a
b1000 A
b1000 X
1!
#12000
0!
#14000
b111100 V
b11110000 '
b11110000 `
02
b11 ;
b11 L
b11 P
01
1-
b11110000 :
b11110000 H
b11110000 R
b11011 Q
b0 S
b10000 <
b10000 F
b10011 0
b10011 N
b0 K
b0 7
b0 I
b0 )
b0 U
b0 _
b10000 *
b10000 ^
b1000 /
b1000 [
b10000 5
b10000 D
b10011 C
b10000 @
b10000 c
b1000000010000010000010011 &
b1000000010000010000010011 B
b10000 ?
b10000 Z
b10000 a
b1100 A
b1100 X
1!
#16000
0!
#18000
x2
b0 ;
b0 L
b0 P
11
0-
b111011 V
b0xxx0xx00 '
b0xxx0xx00 `
b0x00110 Q
b10 S
b0 =
b0 G
b0 M
b11101100 :
b11101100 H
b11101100 R
b11111111111111111111111111111100 <
b11111111111111111111111111111100 F
b100011 0
b100011 N
b1111111 6
b1111111 J
b1010 K
b10 7
b10 I
b11110000 %
b11110000 E
b11110000 +
b11110000 ]
b1000 ,
b1000 \
b10 )
b10 U
b10 _
b1010 *
b1010 ^
b11100 /
b11100 [
b11111111111111111111111111111100 5
b11111111111111111111111111111100 D
b100011 C
b10100 @
b10100 c
b11111110101001000010111000100011 &
b11111110101001000010111000100011 B
b10100 ?
b10100 Z
b10100 a
b10000 A
b10000 X
1!
#20000
0!
#22000
b111100 V
b11110000 '
b11110000 `
02
b11 ;
b11 L
b11 P
01
1-
b11110000 :
b11110000 H
b11110000 R
b11011 Q
b0 S
b0 <
b0 F
b10011 0
b10011 N
b0 6
b0 J
b0 K
b0 7
b0 I
b0 )
b0 U
b0 _
b0 *
b0 ^
b1010 /
b1010 [
b0 5
b0 D
b10011 C
b11000 @
b11000 c
b1000000010100010011 &
b1000000010100010011 B
b11000 ?
b11000 Z
b11000 a
b10100 A
b10100 X
1!
#24000
0!
#26000
b111011 V
b11101100 '
b11101100 `
b11101100 :
b11101100 H
b11101100 R
b1000 K
b11111111111111111111111111111100 <
b11111111111111111111111111111100 F
b1111111 6
b1111111 J
b1010 ,
b1010 \
b11100 *
b11100 ^
b11111111111111111111111111111100 5
b11111111111111111111111111111100 D
b11100 @
b11100 c
b11111111110001010000010100010011 &
b11111111110001010000010100010011 B
b11100 ?
b11100 Z
b11100 a
b11000 A
b11000 X
1!
#28000
b111010 V
b11101000 '
b11101000 `
b11101000 :
b11101000 H
b11101000 R
b11101100 %
b11101100 E
b11101100 +
b11101100 ]
0!
#30000
b10 .
b10 W
b111011 V
b10 '
b10 `
13
12
b0 ;
b0 L
b0 P
b11101100 :
b11101100 H
b11101100 R
b1100011 Q
b10 S
b0 =
b0 G
b0 M
b0 <
b0 F
b11 0
b11 N
b0 6
b0 J
b10 K
b10 7
b10 I
b0 *
b0 ^
b0 5
b0 D
b11 C
b100000 @
b100000 c
b1010010010100000011 &
b1010010010100000011 B
b100000 ?
b100000 Z
b100000 a
b11100 A
b11100 X
1!
#32000
b0 '
b0 `
b0 .
b0 W
b0 V
b10 :
b10 H
b10 R
b10 %
b10 E
b10 +
b10 ]
0!
#34000
03
02
b11 ;
b11 L
b11 P
b11011 Q
b0 S
b0 :
b0 H
b0 R
b10011 0
b10011 N
b0 K
b0 7
b0 I
b0 %
b0 E
b0 +
b0 ]
b0 ,
b0 \
b1011 /
b1011 [
b10011 C
b100100 @
b100100 c
b10110010011 &
b10110010011 B
b100100 ?
b100100 Z
b100100 a
b100000 A
b100000 X
1!
#36000
0!
#38000
b1 =
b1 G
b1 M
18
x2
b1 ;
b1 L
b1 P
09
0-
b0 V
b0x0 '
b0x0 `
b10x01000 Q
b10 :
b10 H
b10 R
b0 <
b0 F
b1100011 0
b1100011 N
b10 %
b10 E
b10 +
b10 ]
b1010 ,
b1010 \
b1011 *
b1011 ^
b1100 /
b1100 [
b1100 5
b1100 D
b1100011 C
b101000 @
b101000 c
b101101010000011001100011 &
b101101010000011001100011 B
b101000 ?
b101000 Z
b101000 a
b100100 A
b100100 X
1!
#40000
0!
#42000
b0 =
b0 G
b0 M
08
02
b11 ;
b11 L
b11 P
19
1-
0(
b0 '
b0 `
b11011 Q
0>
b0 :
b0 H
b0 R
b10011 0
b10011 N
b0 %
b0 E
b0 +
b0 ]
b0 ,
b0 \
b0 *
b0 ^
b1010 /
b1010 [
b0 5
b0 D
b10011 C
b101100 @
b101100 c
b10100010011 &
b10100010011 B
b101100 ?
b101100 Z
b101100 a
b101000 A
b101000 X
1!
#44000
0!
#46000
b1111 =
b1111 G
b1111 M
b0 V
b0 '
b0 `
b1 4
b1 O
x2
bx ;
bx L
bx P
x9
b0 :
b0 H
b0 R
b100xxx0x1 Q
b0xxxxx000 <
b0xxxxx000 F
b1101111 0
b1101111 N
b11110000 )
b11110000 U
b11110000 _
b1000 *
b1000 ^
b0 /
b0 [
b1000 5
b1000 D
b1101111 C
b110000 @
b110000 c
b100000000000000001101111 &
b100000000000000001101111 B
b110000 ?
b110000 Z
b110000 a
b101100 A
b101100 X
1!
#48000
0!
#50000
b1 '
b1 `
b1 :
b1 H
b1 R
b0 =
b0 G
b0 M
b0 4
b0 O
02
b11 ;
b11 L
b11 P
19
b11011 Q
b1 <
b1 F
b10011 0
b10011 N
b11011000 )
b11011000 U
b11011000 _
b1 *
b1 ^
b1010 /
b1010 [
b1 5
b1 D
b10011 C
b110100 @
b110100 c
b100000000010100010011 &
b100000000010100010011 B
b110100 ?
b110100 Z
b110100 a
b110000 A
b110000 X
1!
#52000
0!
#54000
b0 '
b0 `
b0 :
b0 H
b0 R
b0 <
b0 F
b0 )
b0 U
b0 _
b0 *
b0 ^
b0 /
b0 [
b0 5
b0 D
b111000 @
b111000 c
b10011 &
b10011 B
b111000 ?
b111000 Z
b111000 a
b110100 A
b110100 X
1!
#56000
0!
#58000
b1 =
b1 G
b1 M
18
x2
b1 ;
b1 L
b1 P
09
0-
b0 V
b0x '
b0x `
b10x01000 Q
b1 :
b1 H
b1 R
b0 <
b0 F
b1100011 0
b1100011 N
b1 %
b1 E
b1 +
b1 ]
b1010 ,
b1010 \
b10000 /
b10000 [
b10000 5
b10000 D
b1100011 C
b111100 @
b111100 c
b1010000100001100011 &
b1010000100001100011 B
b111100 ?
b111100 Z
b111100 a
b111000 A
b111000 X
1!
#60000
0!
#62000
b0 =
b0 G
b0 M
08
02
b11 ;
b11 L
b11 P
19
1-
b0 '
b0 `
0(
b11011 Q
b0 :
b0 H
b0 R
0>
b10011 0
b10011 N
b0 %
b0 E
b0 +
b0 ]
b0 ,
b0 \
b1010 /
b1010 [
b0 5
b0 D
b10011 C
b1000000 @
b1000000 c
b10100010011 &
b10100010011 B
b1000000 ?
b1000000 Z
b1000000 a
b111100 A
b111100 X
1!
#64000
0!
