src/modules/mux_4x1.v

module mux_4x1
#(parameter DATA_WIDTH = 32)(
  input [1:0] select,
  input [DATA_WIDTH-1:0] in1,
  input [DATA_WIDTH-1:0] in2,
  input [DATA_WIDTH-1:0] in3,
  input [DATA_WIDTH-1:0] in4,
  
  output reg [DATA_WIDTH-1:0] out
);

// combinational logic
always @ (*) begin
  case(select)
    2'b00: out = in1;
    2'b01: out = in2;
    2'b10: out = in3;
    2'b11: out = in4;
    default: out = 32'h0000_0000; // should never fall here
  endcase
end

endmodule

src/modules/data_memory.v
// data_memory.v

module data_memory #(
  parameter DATA_WIDTH = 32, MEM_ADDR_SIZE = 8
)(
  input  clk,
  input  mem_write,
  input  mem_read,
  input  [1:0] maskmode,
  input  sext,
  input  [DATA_WIDTH-1:0] address,
  input  [DATA_WIDTH-1:0] write_data,

  output reg [DATA_WIDTH-1:0] read_data
);

  // memory
  reg [DATA_WIDTH-1:0] mem_array [0:2**MEM_ADDR_SIZE-1]; // change memory size
  initial $readmemh("data/data_memory.mem", mem_array);
  // wire reg for writedata
  wire [MEM_ADDR_SIZE-1:0] address_internal; // 256 = 8-bit address

  assign address_internal = address[MEM_ADDR_SIZE+1:2]; // 256 = 8-bit address

  // update at negative edge
  always @(negedge clk) begin 
    if (mem_write == 1'b1) begin
      ////////////////////////////////////////////////////////////////////////
      // TODO : Perform writes (select certain bits from write_data
      // according to maskmode
      ////////////////////////////////////////////////////////////////////////
		case (maskmode)
			// store byte (1B)
			2'b00: mem_array[address_internal][7:0] = write_data[7:0];
			// store half-word (2B)
			2'b01: mem_array[address_internal][15:0] = write_data[15:0];
			// store word (4B)
			2'b10: mem_array[address_internal][31:0] = write_data[31:0];
		endcase	
	// TODO END
    end
  end

  // combinational logic
  always @(*) begin
    if (mem_read == 1'b1) begin
      ////////////////////////////////////////////////////////////////////////
      // TODO : Perform reads (select bits according to sext & maskmode)
      ////////////////////////////////////////////////////////////////////////
		case ({sext, maskmode})
			// load byte
			3'b0_00: read_data = {{24{mem_array[address_internal][7]}}, mem_array[address_internal][7:0]};
			// load half-word
			3'b0_01: read_data = {{16{mem_array[address_internal][15]}}, mem_array[address_internal][15:0]};
			// load word
			3'b0_10: read_data = mem_array[address_internal];
			// load byte Unsigned
			3'b1_00: read_data = {{24{1'b0}}, mem_array[address_internal][7:0]};
			// load half-word Unsigned
			3'b1_01: read_data = {{16{1'b0}}, mem_array[address_internal][15:0]};
		endcase
		// TODO END
    end else begin
      read_data = 32'h0000_0000;
    end
  end

endmodule

src/modules/branch_control.v
module branch_control
(
  // current pc
  input branch,
  input check,

  output reg taken 
);

///////////////////////////////////////////////////////////////////////////////
// TODO : You need to do something!
//////////////////////////////////////////////////////////////////////////////
always @(*) begin
	taken = branch & check;
end

endmodule

src/modules/defines.v
`ifndef __defines_vh__
`define __defines_vh__

// ALU function
`define OP_ADD  4'b0000
`define OP_SUB  4'b0001
`define OP_XOR  4'b0010
`define OP_OR   4'b0011
`define OP_AND  4'b0100
`define OP_SLL  4'b0101
`define OP_SRL  4'b0110
`define OP_SRA  4'b0111
`define OP_SLT  4'b1000
`define OP_SLTU 4'b1001
`define OP_BGE   4'b1010
`define OP_BGEU   4'b1011

`define OP_EEE  4'b1111   // error

`endif // __defines_vh__

src/modules/ALU.v
// ALU.v

// This module performs ALU operations according to the "alu_func" value,
// which is generated by the ALU control unit.
// Note that there exist 10 R-type instructions in RV32I:
// add, sub, xor, or, and, sll, srl, sra, slt, sltu

`include "defines.v"

module ALU 
#(parameter DATA_WIDTH = 32)(
  input [DATA_WIDTH-1:0] in_a, 
  input [DATA_WIDTH-1:0] in_b,
  input [3:0] alu_func,

  output reg [DATA_WIDTH-1:0] result,
  output reg check 
);

// combinational logic 
always @(*) begin
  case (alu_func)
    `OP_ADD:  result = in_a +  in_b; 
    `OP_SUB:  result = in_a -  in_b;
    `OP_XOR:  result = in_a ^  in_b;
    `OP_OR:   result = in_a |  in_b;
    `OP_AND:  result = in_a &  in_b;
    /////////////////////////////////////////////////////////////////////////
    // TODO : Add other operations
    // - The example below is given as a hint
    // - `OP_SRA: result = $signed(in_a) >>> in_b[4:0];
    /////////////////////////////////////////////////////////////////////////
	`OP_SLL: result = in_a << in_b[4:0];
    `OP_SRL: result = in_a >> in_b[4:0];
    `OP_SRA: result = $signed(in_a) >>> in_b[4:0];
    `OP_SLT: result = ($signed(in_a) < $signed(in_b)) ? 1:0;
    `OP_SLTU: result = (in_a < in_b) ? 1:0;
	// TODO END
    default:  result = 32'h0000_0000;
  endcase
end

// combinational logic
always @(*) begin
  case (alu_func)
    //////////////////////////////////////////////////////////////////////////
    // TODO : Generate check signal
    //////////////////////////////////////////////////////////////////////////
    `OP_SUB: check = (in_a - in_b == 0) ? 1:0;
	// TODO END
	default:  check = 1'b0;
  endcase
end
endmodule

src/modules/ALU_control.v
// ALU_control.v

/* This unit generates a 4-bit ALU control input (alu_func)
 * based on the 2-bit ALUOp control, funct7, and funct3 field.
 *
 * ALUOp | ALU action | notes  
 * ------|------------|---------------------
 *   00  | add        | for loads and stores
 *   01  | subtract   | for branches
 *   10  | it varies  | for R-types
 *   11  | it varies  | immediate
 *
 * R-type instructions (opcode: 0110011)
 * Name | funct3 | funct7
 * -----------------------
 * add  |  0x0   | 0x00
 * sub  |  0x0   | 0x20
 * xor  |  0x4   | 0x00
 * or   |  0x6   | 0x00
 * and  |  0x7   | 0x00
 * sll  |  0x1   | 0x00
 * srl  |  0x5   | 0x00
 * sra  |  0x5   | 0x20
 * slt  |  0x2   | 0x00
 * sltu |  0x3   | 0x00
 */

`include "defines.v"

module ALU_control(
  input wire [1:0] alu_op,
  input wire [6:0] funct7,
  input wire [2:0] funct3,

  output reg [3:0] alu_func
);

wire [3:0] funct;
assign funct = {funct7[5], funct3};

// combinational logic
always @(*) begin
  case (alu_op)
    2'b00: begin
    ///////////////////////////////////////////////////////////////////////
    // TODO : select operation for loads/stores
    ///////////////////////////////////////////////////////////////////////
		alu_func = `OP_ADD;
	//TODO END
    end
    2'b01: begin
    ///////////////////////////////////////////////////////////////////////
    // TODO : select operation for branches
    ///////////////////////////////////////////////////////////////////////
		case (funct3)
			3'b000: alu_func = `OP_SUB; //beq
			3'b001: alu_func = `OP_ADD; //bne
			3'b100: alu_func = `OP_SLT; //blt
			3'b101: alu_func = `OP_BGE; //bge
			3'b110: alu_func = `OP_SLTU; //bltu
			3'b111: alu_func = `OP_BGEU; //bgeu
		endcase
	// TODO END
    end
    2'b10: begin                // R-types
      case (funct)
        4'b0_000: alu_func = `OP_ADD;
        4'b1_000: alu_func = `OP_SUB;
        4'b0_100: alu_func = `OP_XOR;
        4'b0_110: alu_func = `OP_OR;
        4'b0_111: alu_func = `OP_AND;
        4'b0_001: alu_func = `OP_SLL;
        4'b0_101: alu_func = `OP_SRL;
        4'b1_101: alu_func = `OP_SRA;
        4'b0_010: alu_func = `OP_SLT;
        4'b0_011: alu_func = `OP_SLTU;
        default:  alu_func = `OP_EEE;  // shoud not fall here 
      endcase
    end
    2'b11: begin
      ///////////////////////////////////////////////////////////////////////
      // TODO : select operation for I-types with immediate
      ///////////////////////////////////////////////////////////////////////
	casex (funct)
		4'bx_000: alu_func = `OP_ADD;
		4'bx_100: alu_func = `OP_XOR;
		4'bx_110: alu_func = `OP_OR;
		4'bx_111: alu_func = `OP_AND;
		4'b0_001: alu_func = `OP_SLL;
		4'b0_101: alu_func = `OP_SRL;
		4'b1_101: alu_func = `OP_SRA;
		4'bx_010: alu_func = `OP_SLT;
		4'bx_011: alu_func = `OP_SLTU;
		default: alu_func = `OP_EEE;
	endcase
    end
    default: alu_func = `OP_EEE;       // should not fall here
  endcase
end

endmodule

src/modules/imm_generator.v
// imm_generator.v

module imm_generator #(
  parameter DATA_WIDTH = 32
)(
  input [31:0] instruction,

  output reg [DATA_WIDTH-1:0] sextimm
);

wire [6:0] opcode;
assign opcode = instruction[6:0];

always @(*) begin
  case (opcode)
    //////////////////////////////////////////////////////////////////////////
    // TODO : Generate sextimm using instruction
    //////////////////////////////////////////////////////////////////////////
	// immediate Arithmetic (I-type)
	7'b001_0011: sextimm = {{20{instruction[31]}}, instruction[31:20]};
	// Load (I-type)
	7'b000_0011: sextimm = {{20{instruction[31]}}, instruction[31:20]};
	//Store (S-type)
    7'b010_0011: sextimm = {{20{instruction[31]}}, instruction[31:25], instruction[11:7]};
	//Branch (B-type)
	7'b110_0011: sextimm = {{19{instruction[31]}}, instruction[31], instruction[7], instruction[30:25], instruction[11:8], 1'b0};
	// Jump and Link (J-type)
	7'b110_1111: sextimm = {{11{instruction[31]}}, instruction[31], instruction[19:12], instruction[20], instruction[30:21], 1'b0};
	// Jump and Link Reg (I-type)
	7'b110_0111: sextimm = {{20{instruction[31]}}, instruction[31:20]};
	
	// TODO END
	
	default:     sextimm = 32'h0000_0000;
  endcase
end


endmodule

src/modules/register_file.v
// register_file.v
// this models 32, 32-bit registers

module register_file #(
  parameter DATA_WIDTH = 32,
  parameter ADDR_WIDTH = 5
)(
  input clk, 
  input  [ADDR_WIDTH-1:0] rs1, 
  input  [ADDR_WIDTH-1:0] rs2, 
  input  [ADDR_WIDTH-1:0] rd,
  input reg_write, 
  input  [DATA_WIDTH-1:0] write_data,

  output [DATA_WIDTH-1:0] rs1_out,
  output [DATA_WIDTH-1:0] rs2_out
);

  // memory array
  reg [DATA_WIDTH-1:0] reg_array[0:2**ADDR_WIDTH-1];
  initial $readmemh("data/register.mem", reg_array); // change initial register file for fib example

  // update regfile at the falling edge
  always @(negedge clk) begin 
    if (reg_write == 1'b1) reg_array[rd] <= write_data;
    reg_array[0] <= 0; // x0 is always zero in RISC-V
  end

  assign rs1_out = reg_array[rs1];
  assign rs2_out = reg_array[rs2];

endmodule

src/modules/control.v
// control.v

// The main control module takes as input the opcode field of an instruction
// (i.e., instruction[6:0]) and generates a set of control signals.

module control(
  input [6:0] opcode,

  output [1:0] jump,
  output branch,
  output mem_read,
  output mem_to_reg,
  output [1:0] alu_op,
  output mem_write,
  output alu_src,
  output reg_write
);

reg [9:0] controls;

// combinational logic
always @(*) begin
  case (opcode)
    7'b0110011: controls = 10'b00_000_10_001; // R-type
     
    //////////////////////////////////////////////////////////////////////////
    // TODO : Implement signals for other instruction types
    //////////////////////////////////////////////////////////////////////////
	7'b0010011: controls = 10'b00_000_11_011;//I-type
	7'b0000011: controls = 10'b00_011_00_011;//Load (I)
	7'b0100011: controls = 10'b00_00x_00_110;//Store (S)
	7'b1100011: controls = 10'b00_10x_01_000;//B-type
	7'b1101111: controls = 10'b10_000_00_0x1;//JAL (J)
	7'b1100111: controls = 10'b11_000_00_0x1;//JALR (I)
	// TODO END
    default:    controls = 10'b00_000_00_000;
  endcase
end

assign {jump, branch, mem_read, mem_to_reg, alu_op, mem_write, alu_src, reg_write} = controls;

endmodule

src/modules/adder.v
module adder #(
  parameter DATA_WIDTH = 32
)(
  input [DATA_WIDTH-1:0] in_a,
  input [DATA_WIDTH-1:0] in_b,

  output reg [DATA_WIDTH-1:0] result
);

// combinational logic
always @(*) begin
  result = in_a + in_b;
end

endmodule

src/simple_cpu.v
// simple_cpu.v
// a single-cycle RISC-V microarchitecture (RV32I)

module simple_cpu
#(parameter DATA_WIDTH = 32)(
  input clk,
  input rstn
);


////////////////////////////////////////////////////
// Instruction Fetch (IF)
////////////////////////////////////////////////////


/* m_next_pc_adder */
wire [DATA_WIDTH-1:0] PC_PLUS_4;
reg [DATA_WIDTH-1:0] PC;    // program counter (32 bits)

adder m_next_pc_adder(
  .in_a(PC),
  .in_b(32'h0000_0004),

  .result(PC_PLUS_4)
);

/* pc: update program counter */
wire [DATA_WIDTH-1:0] NEXT_PC;

always @(posedge clk) begin
  if (rstn == 1'b0) PC <= 32'h00000000;
  else PC <= NEXT_PC;
end


/* inst_memory: memory where instruction lies */
localparam NUM_INSTS = 64;

reg [31:0] inst_memory[0:NUM_INSTS-1];
initial $readmemb("data/inst.mem", inst_memory);


/* instruction: current instruction */
wire [DATA_WIDTH-1:0] instruction;
assign instruction = inst_memory[PC[7:2]]; // 64 inst


////////////////////////////////////////////////////
// Instruction Decode (ID)
////////////////////////////////////////////////////


// from register file 
wire [31:0] rs1_out, rs2_out;
wire [31:0] alu_out;

// 5 bits for each (because there exist 32 registers)
wire [4:0] rs1, rs2, rd;

wire [6:0] opcode;
wire [6:0] funct7;
wire [2:0] funct3;

// instruction fields
assign opcode = instruction[6:0];

assign funct7 = instruction[31:25];
assign funct3 = instruction[14:12];

// R type
assign rs1 = instruction[19:15];
assign rs2 = instruction[24:20];
assign rd  = instruction[11:7];

/* m_control: control unit */
wire branch;
wire mem_read;
wire mem_to_reg;
wire [1:0] alu_op;
wire mem_write;
wire alu_src;
wire reg_write;
wire [1:0] jump;

control m_control(
  .opcode(opcode),

  .jump(jump),
  .branch(branch),
  .mem_read(mem_read),
  .mem_to_reg(mem_to_reg),
  .alu_op(alu_op),
  .mem_write(mem_write),
  .alu_src(alu_src),
  .reg_write(reg_write)
);

/* m_register_file: register file */
wire [DATA_WIDTH-1:0] write_data; 
wire [DATA_WIDTH-1:0] read_data;

register_file m_register_file(
  .clk(clk),
  .rs1(rs1),
  .rs2(rs2),
  .rd(rd),
  .reg_write(reg_write),
  .write_data(write_data),
  
  .rs1_out(rs1_out),
  .rs2_out(rs2_out)
);

///////////////////////////////////////////////////////////////////////////////
// TODO : Immediate Generator
//////////////////////////////////////////////////////////////////////////////
wire signed [31:0] immediate;

imm_generator imm_generator(
	.instruction(instruction),
	
	.sextimm(immediate)
);

////////////////////////////////////////////////////
// Execute (EX) 
////////////////////////////////////////////////////


/* m_ALU_control: ALU control unit */
wire [3:0] alu_func;

ALU_control m_ALU_control(
  .alu_op(alu_op), 
  .funct7(funct7),
  .funct3(funct3),

  .alu_func(alu_func)
);

wire [31:0] alu_in2;

///////////////////////////////////////////////////////////////////////////////
// TODO : Need a fix
//////////////////////////////////////////////////////////////////////////////
assign alu_in2 = (alu_src == 0) ? rs2_out:immediate;
// TODO END
//////////////////////////////////////////////////////////////////////////////

/* m_ALU: ALU */
wire [31:0] alu_in1;
wire alu_check;

assign alu_in1 = rs1_out;

ALU m_ALU(
  .in_a(alu_in1), 
  .in_b(alu_in2), // is input with reg allowed?? 
  .alu_func(alu_func),

  // output
  .result(alu_out),
  .check(alu_check)
);


////////////////////////////////////////////////////
// Memory (MEM) 
////////////////////////////////////////////////////

/* m_branch_control: generate taken for branch instruction */
wire taken;

branch_control m_branch_control(
  .branch(branch),
  .check(alu_check),

  .taken(taken)
);

///////////////////////////////////////////////////////////////////////////////
// TODO : Currently, NEXT_PC is always PC_PLUS_4. Using adders and muxes & 
// control signals, compute & assign the correct NEXT_PC.
//////////////////////////////////////////////////////////////////////////////
wire [31:0] PC_target = {1'b0, PC} + immediate;
wire [31:0] PC_target_ind = $signed(rs1_out) + immediate;
reg [31:0] tmp_PC;

always @(*) begin
	casex ({jump,taken})
		3'b000: tmp_PC = PC+32'd4;
		3'b001: tmp_PC = PC_target;
		3'b10x: tmp_PC = PC_target;
		3'b11x: tmp_PC = {PC_target_ind[31:1], 1'b0};
		default: tmp_PC = PC+32'd4;
	endcase
end
assign NEXT_PC = tmp_PC;
/*
mux_4x1 mux_PC(
	.select({jump[0], taken}),
	.in1(PC_PLUS_4), //00
	.in2(PC_target), //01
	.in3(), //10
	.in4(), //11

	.out(NEXT_PC)
);*/
// TODO END


///////////////////////////////////////////////////////////////////////////////
// TODO : Feed the appropriate inputs to the data memory
//////////////////////////////////////////////////////////////////////////////
/* m_data_memory: data memory */

data_memory m_data_memory(
  .clk(clk),
  .mem_write(mem_write),
  .mem_read(mem_read),
  .maskmode(funct3[1:0]),
  .sext(funct3[2]),
  .address(alu_out),
  .write_data(rs2_out),

  .read_data(read_data)
);
// TODO END
//////////////////////////////////////////////////////////////////////////////


////////////////////////////////////////////////////
// Write Back (WB) 
////////////////////////////////////////////////////

///////////////////////////////////////////////////////////////////////////////
// TODO : Need a fix
//////////////////////////////////////////////////////////////////////////////

mux_4x1 mux_WriteBack(
	.select({jump[1],mem_to_reg}),
	.in1(alu_out),
	.in2(read_data),
	.in3(PC_PLUS_4),
	.in4(PC_PLUS_4),

	.out(write_data)
);
// TODO END

//////////////////////////////////////////////////////////////////////////////
endmodule

src/riscv_tb.v
`timescale 1 ns/10 ps

module riscv_tb;

reg clk, rstn;
wire [31:0] inst;

integer i;

initial begin
  clk  = 1'b0;
  rstn = 1'b0;
  $display($time, " ** Start Simulation **");
  $display($time, " Instruction Memory ");
  for (i=0;i<64;i=i+1) $display($time, " INST[%2d]: %b", i, my_cpu.inst_memory[i]);
  $monitor($time, " [PC] pc : %d", my_cpu.PC);
  #60 rstn = 1'b1;
  #3760; // for Fibonacci example
  rstn = 1'b0;
  $display($time, " ** End Simulation **");
  $display($time, " REGISTER FILE");
  for (i=0;i<32;i=i+1) $display($time, " Reg[%d]: %d (%b)", i, $signed(my_cpu.m_register_file.reg_array[i]), my_cpu.m_register_file.reg_array[i]);
  $display($time, " DATA MEMORY");
  for (i=0;i<128;i=i+1) $display($time, " Mem[%d]: %d (%b)", i, $signed(my_cpu.m_data_memory.mem_array[i]), my_cpu.m_data_memory.mem_array[i]);
  $finish;
end

always begin
  #20 clk = ~clk;
end

// dump the state of the design
// VCD (Value Change Dump) is a standard dump format defined in Verilog.
initial begin
  $dumpfile("sim.vcd");
  $dumpvars(0, riscv_tb);
end

simple_cpu my_cpu(.clk(clk), .rstn(rstn));

endmodule

sim.vcd
$date
	Thu Apr  7 11:47:15 2022
$end
$version
	Icarus Verilog
$end
$timescale
	10ps
$end
$scope module riscv_tb $end
$var reg 1 ! clk $end
$var reg 1 " rstn $end
$var integer 32 # i [31:0] $end
$scope module my_cpu $end
$var wire 32 $ NEXT_PC [31:0] $end
$var wire 32 % alu_in1 [31:0] $end
$var wire 1 ! clk $end
$var wire 32 & instruction [31:0] $end
$var wire 1 " rstn $end
$var wire 32 ' write_data [31:0] $end
$var wire 1 ( taken $end
$var wire 32 ) rs2_out [31:0] $end
$var wire 5 * rs2 [4:0] $end
$var wire 32 + rs1_out [31:0] $end
$var wire 5 , rs1 [4:0] $end
$var wire 1 - reg_write $end
$var wire 32 . read_data [31:0] $end
$var wire 5 / rd [4:0] $end
$var wire 7 0 opcode [6:0] $end
$var wire 1 1 mem_write $end
$var wire 1 2 mem_to_reg $end
$var wire 1 3 mem_read $end
$var wire 2 4 jump [1:0] $end
$var wire 32 5 immediate [31:0] $end
$var wire 7 6 funct7 [6:0] $end
$var wire 3 7 funct3 [2:0] $end
$var wire 1 8 branch $end
$var wire 1 9 alu_src $end
$var wire 32 : alu_out [31:0] $end
$var wire 2 ; alu_op [1:0] $end
$var wire 32 < alu_in2 [31:0] $end
$var wire 4 = alu_func [3:0] $end
$var wire 1 > alu_check $end
$var wire 32 ? PC_target_ind [31:0] $end
$var wire 32 @ PC_target [31:0] $end
$var wire 32 A PC_PLUS_4 [31:0] $end
$var reg 32 B PC [31:0] $end
$var reg 32 C tmp_PC [31:0] $end
$scope module imm_generator $end
$var wire 32 D instruction [31:0] $end
$var wire 7 E opcode [6:0] $end
$var reg 32 F sextimm [31:0] $end
$upscope $end
$scope module m_ALU $end
$var wire 32 G in_a [31:0] $end
$var wire 32 H in_b [31:0] $end
$var wire 4 I alu_func [3:0] $end
$var reg 1 > check $end
$var reg 32 J result [31:0] $end
$upscope $end
$scope module m_ALU_control $end
$var wire 3 K funct3 [2:0] $end
$var wire 7 L funct7 [6:0] $end
$var wire 4 M funct [3:0] $end
$var wire 2 N alu_op [1:0] $end
$var reg 4 O alu_func [3:0] $end
$upscope $end
$scope module m_branch_control $end
$var wire 1 > check $end
$var wire 1 8 branch $end
$var reg 1 ( taken $end
$upscope $end
$scope module m_control $end
$var wire 7 P opcode [6:0] $end
$var wire 1 - reg_write $end
$var wire 1 1 mem_write $end
$var wire 1 2 mem_to_reg $end
$var wire 1 3 mem_read $end
$var wire 2 Q jump [1:0] $end
$var wire 1 8 branch $end
$var wire 1 9 alu_src $end
$var wire 2 R alu_op [1:0] $end
$var reg 10 S controls [9:0] $end
$upscope $end
$scope module m_data_memory $end
$var wire 32 T address [31:0] $end
$var wire 1 ! clk $end
$var wire 2 U maskmode [1:0] $end
$var wire 1 3 mem_read $end
$var wire 1 1 mem_write $end
$var wire 1 V sext $end
$var wire 32 W write_data [31:0] $end
$var wire 8 X address_internal [7:0] $end
$var reg 32 Y read_data [31:0] $end
$upscope $end
$scope module m_next_pc_adder $end
$var wire 32 Z in_a [31:0] $end
$var wire 32 [ in_b [31:0] $end
$var reg 32 \ result [31:0] $end
$upscope $end
$scope module m_register_file $end
$var wire 1 ! clk $end
$var wire 5 ] rd [4:0] $end
$var wire 1 - reg_write $end
$var wire 5 ^ rs1 [4:0] $end
$var wire 32 _ rs1_out [31:0] $end
$var wire 5 ` rs2 [4:0] $end
$var wire 32 a rs2_out [31:0] $end
$var wire 32 b write_data [31:0] $end
$upscope $end
$scope module mux_WriteBack $end
$var wire 32 c in1 [31:0] $end
$var wire 32 d in2 [31:0] $end
$var wire 32 e in3 [31:0] $end
$var wire 32 f in4 [31:0] $end
$var wire 2 g select [1:0] $end
$var reg 32 h out [31:0] $end
$upscope $end
$upscope $end
$upscope $end
$enddefinitions $end
#0
$dumpvars
b0 h
bx g
bx f
bx e
b0 d
bx c
b0 b
bx a
bx `
bx _
bx ^
bx ]
bx \
b100 [
bx Z
b0 Y
bx X
bx W
xV
bx U
bx T
bx S
bx R
bx Q
bx P
bx O
bx N
bx M
bx L
bx K
bx J
bx I
bx H
bx G
bx F
bx E
bx D
bx C
bx B
bx A
bx @
bx ?
x>
bx =
bx <
bx ;
bx :
x9
x8
bx 7
bx 6
bx 5
bx 4
x3
x2
x1
bx 0
bx /
b0 .
x-
bx ,
bx +
bx *
bx )
x(
b0 '
bx &
bx %
bx $
b1000000 #
0"
0!
$end
#2000
b11100000 '
b11100000 b
b11100000 h
b0 4
b0 Q
08
03
b0 g
02
b11 ;
b11 N
b11 R
01
19
1-
0(
b111000 X
b11011 S
b0 U
0V
b0 =
b0 I
b0 O
1>
b11100000 :
b11100000 J
b11100000 T
b11100000 c
b11111111111111111111111111100000 @
b11111111111111111111111111100000 <
b11111111111111111111111111100000 H
b10011 0
b10011 P
b1111111 6
b1111111 L
b1000 M
b0 7
b0 K
b11100000 ?
b100000000 %
b100000000 G
b100000000 +
b100000000 _
b10 ,
b10 ^
b0 )
b0 W
b0 a
b0 *
b0 `
b10 /
b10 ]
b11111111111111111111111111100000 5
b11111111111111111111111111100000 F
b10011 E
b11111110000000010000000100010011 &
b11111110000000010000000100010011 D
b100 A
b100 \
b100 e
b100 f
b100 $
b100 C
b0 B
b0 Z
1!
#4000
b110000 X
b11000000 '
b11000000 b
b11000000 h
b11000000 :
b11000000 J
b11000000 T
b11000000 c
b11000000 ?
b11100000 %
b11100000 G
b11100000 +
b11100000 _
0!
#6000
b111111 X
b0 '
b0 b
b0 h
b0x g
x2
b0 ;
b0 N
b0 R
11
0-
1>
b11111100 :
b11111100 J
b11111100 T
b11111100 c
b0x00110 S
b10 U
b0 =
b0 I
b0 O
b11100 <
b11100 H
b100011 0
b100011 P
b0 6
b0 L
b10 M
b10 7
b10 K
b1000 *
b1000 `
b11100 /
b11100 ]
b11111100 ?
b11100 5
b11100 F
b100011 E
b100000010010111000100011 &
b100000010010111000100011 D
b100000 @
b1000 A
b1000 \
b1000 e
b1000 f
b1000 $
b1000 C
b100 B
b100 Z
1!
1"
#8000
0!
#10000
b111110 X
b11111000 :
b11111000 J
b11111000 T
b11111000 c
b11000 <
b11000 H
b11011000 )
b11011000 W
b11011000 a
b1 *
b1 `
b11000 /
b11000 ]
b11111000 ?
b11000 5
b11000 F
b100010010110000100011 &
b100010010110000100011 D
b100000 @
b1100 A
b1100 \
b1100 e
b1100 f
b1100 $
b1100 C
b1000 B
b1000 Z
1!
#12000
0!
#14000
b111100 X
b11110000 '
b11110000 b
b11110000 h
b0 g
02
b11 ;
b11 N
b11 R
01
1-
b11110000 :
b11110000 J
b11110000 T
b11110000 c
b11011 S
b0 U
b10000 <
b10000 H
b10011 0
b10011 P
b0 M
b0 7
b0 K
b0 )
b0 W
b0 a
b10000 *
b10000 `
b1000 /
b1000 ]
b11110000 ?
b10000 5
b10000 F
b10011 E
b1000000010000010000010011 &
b1000000010000010000010011 D
b11100 @
b10000 A
b10000 \
b10000 e
b10000 f
b10000 $
b10000 C
b1100 B
b1100 Z
1!
#16000
0!
#18000
b0x g
x2
b0 ;
b0 N
b0 R
11
0-
1>
b111011 X
b0 '
b0 b
b0 h
b0x00110 S
b10 U
b0 =
b0 I
b0 O
b11101100 :
b11101100 J
b11101100 T
b11101100 c
b11111111111111111111111111111100 <
b11111111111111111111111111111100 H
b100011 0
b100011 P
b1111111 6
b1111111 L
b1010 M
b10 7
b10 K
b11110000 %
b11110000 G
b11110000 +
b11110000 _
b1000 ,
b1000 ^
b10 )
b10 W
b10 a
b1010 *
b1010 `
b11100 /
b11100 ]
b11101100 ?
b11111111111111111111111111111100 5
b11111111111111111111111111111100 F
b100011 E
b11111110101001000010111000100011 &
b11111110101001000010111000100011 D
b1100 @
b10100 A
b10100 \
b10100 e
b10100 f
b10100 $
b10100 C
b10000 B
b10000 Z
1!
#20000
0!
#22000
b111100 X
b11110000 '
b11110000 b
b11110000 h
b0 g
02
b11 ;
b11 N
b11 R
01
1-
b11110000 :
b11110000 J
b11110000 T
b11110000 c
b11011 S
b0 U
b0 <
b0 H
b10011 0
b10011 P
b0 6
b0 L
b0 M
b0 7
b0 K
b0 )
b0 W
b0 a
b0 *
b0 `
b1010 /
b1010 ]
b11110000 ?
b0 5
b0 F
b10011 E
b1000000010100010011 &
b1000000010100010011 D
b10100 @
b11000 A
b11000 \
b11000 e
b11000 f
b11000 $
b11000 C
b10100 B
b10100 Z
1!
#24000
0!
#26000
b111011 X
b11101100 '
b11101100 b
b11101100 h
b11101100 :
b11101100 J
b11101100 T
b11101100 c
b1000 M
b11111111111111111111111111111100 <
b11111111111111111111111111111100 H
b1111111 6
b1111111 L
b1010 ,
b1010 ^
b11100 *
b11100 `
b11101100 ?
b11111111111111111111111111111100 5
b11111111111111111111111111111100 F
b11111111110001010000010100010011 &
b11111111110001010000010100010011 D
b10100 @
b11100 A
b11100 \
b11100 e
b11100 f
b11100 $
b11100 C
b11000 B
b11000 Z
1!
#28000
b111010 X
b11101000 '
b11101000 b
b11101000 h
b11101000 :
b11101000 J
b11101000 T
b11101000 c
b11101000 ?
b11101100 %
b11101100 G
b11101100 +
b11101100 _
0!
#30000
b10 .
b10 Y
b10 d
b111011 X
b10 '
b10 b
b10 h
13
b1 g
12
b0 ;
b0 N
b0 R
1>
b11101100 :
b11101100 J
b11101100 T
b11101100 c
b1100011 S
b10 U
b0 =
b0 I
b0 O
b0 <
b0 H
b11 0
b11 P
b0 6
b0 L
b10 M
b10 7
b10 K
b0 *
b0 `
b11101100 ?
b0 5
b0 F
b11 E
b1010010010100000011 &
b1010010010100000011 D
b11100 @
b100000 A
b100000 \
b100000 e
b100000 f
b100000 $
b100000 C
b11100 B
b11100 Z
1!
#32000
b0 '
b0 b
b0 h
b0 .
b0 Y
b0 d
b0 X
b10 :
b10 J
b10 T
b10 c
b10 ?
b10 %
b10 G
b10 +
b10 _
0!
#34000
03
b0 g
02
b11 ;
b11 N
b11 R
b11011 S
b0 U
b0 :
b0 J
b0 T
b0 c
0>
b10011 0
b10011 P
b0 M
b0 7
b0 K
b0 ?
b0 %
b0 G
b0 +
b0 _
b0 ,
b0 ^
b1011 /
b1011 ]
b10011 E
b10110010011 &
b10110010011 D
b100000 @
b100100 A
b100100 \
b100100 e
b100100 f
b100100 $
b100100 C
b100000 B
b100000 Z
1!
#36000
0!
#38000
0(
b1 =
b1 I
b1 O
18
b0x g
x2
b1 ;
b1 N
b1 R
09
0-
b0 X
b0 '
b0 b
b0 h
b10x01000 S
0>
b10 :
b10 J
b10 T
b10 c
b0 <
b0 H
b1100011 0
b1100011 P
b10 %
b10 G
b10 +
b10 _
b1010 ,
b1010 ^
b1011 *
b1011 `
b1100 /
b1100 ]
b1110 ?
b1100 5
b1100 F
b1100011 E
b101101010000011001100011 &
b101101010000011001100011 D
b110000 @
b101000 A
b101000 \
b101000 e
b101000 f
b101000 $
b101000 C
b100100 B
b100100 Z
1!
#40000
0!
#42000
b0 =
b0 I
b0 O
08
b0 g
02
b11 ;
b11 N
b11 R
19
1-
0(
b11011 S
0>
b0 :
b0 J
b0 T
b0 c
b10011 0
b10011 P
b0 %
b0 G
b0 +
b0 _
b0 ,
b0 ^
b0 *
b0 `
b1010 /
b1010 ]
b0 ?
b0 5
b0 F
b10011 E
b10100010011 &
b10100010011 D
b101000 @
b101100 A
b101100 \
b101100 e
b101100 f
b101100 $
b101100 C
b101000 B
b101000 Z
1!
#44000
0!
#46000
b10 g
bx X
b110000 '
b110000 b
b110000 h
b10 4
b10 Q
b0 ;
b0 N
b0 R
x9
x>
bx :
bx J
bx T
bx c
b10000000x1 S
b0xxxxx000 <
b0xxxxx000 H
b1101111 0
b1101111 P
b11110000 )
b11110000 W
b11110000 a
b1000 *
b1000 `
b0 /
b0 ]
b1000 ?
b1000 5
b1000 F
b1101111 E
b100000000000000001101111 &
b100000000000000001101111 D
b110100 @
b110000 A
b110000 \
b110000 e
b110000 f
b110100 $
b110100 C
b101100 B
b101100 Z
1!
#48000
b1000 ?
b0 %
b0 G
b0 +
b0 _
0!
