src/modules/data_memory.v
// data_memory.v

module data_memory #(
  parameter DATA_WIDTH = 32, MEM_ADDR_SIZE = 8
)(
  input  clk,
  input  mem_write,
  input  mem_read,
  input  [1:0] maskmode,
  input  sext,
  input  [DATA_WIDTH-1:0] address,
  input  [DATA_WIDTH-1:0] write_data,

  output reg [DATA_WIDTH-1:0] read_data
);

  // memory
  reg [DATA_WIDTH-1:0] mem_array [0:2**MEM_ADDR_SIZE-1]; // change memory size
  initial $readmemh("data/data_memory.mem", mem_array);
  // wire reg for writedata
  wire [MEM_ADDR_SIZE-1:0] address_internal; // 256 = 8-bit address

  assign address_internal = address[MEM_ADDR_SIZE+1:2]; // 256 = 8-bit address

  // update at negative edge
  always @(negedge clk) begin 
    if (mem_write == 1'b1) begin
      ////////////////////////////////////////////////////////////////////////
      // TODO : Perform writes (select certain bits from write_data
      // according to maskmode
      ////////////////////////////////////////////////////////////////////////
    end
  end

  // combinational logic
  always @(*) begin
    if (mem_read == 1'b1) begin
      ////////////////////////////////////////////////////////////////////////
      // TODO : Perform reads (select bits according to sext & maskmode)
      ////////////////////////////////////////////////////////////////////////
    end else begin
      read_data = 32'h0000_0000;
    end
  end

endmodule

src/modules/branch_control.v
module branch_control
(
  // current pc
  input branch,
  input check,

  output reg taken 
);

///////////////////////////////////////////////////////////////////////////////
// TODO : You need to do something!
//////////////////////////////////////////////////////////////////////////////

endmodule

src/modules/defines.v
`ifndef __defines_vh__
`define __defines_vh__

// ALU function
`define OP_ADD  4'b0000
`define OP_SUB  4'b0001
`define OP_XOR  4'b0010
`define OP_OR   4'b0011
`define OP_AND  4'b0100
`define OP_SLL  4'b0101
`define OP_SRL  4'b0110
`define OP_SRA  4'b0111
`define OP_SLT  4'b1000
`define OP_SLTU 4'b1001
`define OP_BGE   4'b1010
`define OP_BGEU   4'b1011

`define OP_EEE  4'b1111   // error

`endif // __defines_vh__

src/modules/ALU.v
// ALU.v

// This module performs ALU operations according to the "alu_func" value,
// which is generated by the ALU control unit.
// Note that there exist 10 R-type instructions in RV32I:
// add, sub, xor, or, and, sll, srl, sra, slt, sltu

`include "defines.v"

module ALU 
#(parameter DATA_WIDTH = 32)(
  input [DATA_WIDTH-1:0] in_a, 
  input [DATA_WIDTH-1:0] in_b,
  input [3:0] alu_func,

  output reg [DATA_WIDTH-1:0] result,
  output reg check 
);

// combinational logic 
always @(*) begin
  case (alu_func)
    `OP_ADD:  result = in_a +  in_b; 
    `OP_SUB:  result = in_a -  in_b;
    `OP_XOR:  result = in_a ^  in_b;
    `OP_OR:   result = in_a |  in_b;
    `OP_AND:  result = in_a &  in_b;

    //////////////////////////////////////////////////////////////////////////
    // TODO : Add other operations
    // - The example below is given as a hint
    // - `OP_SRA: result = $signed(in_a) >>> in_b[4:0];
    //////////////////////////////////////////////////////////////////////////
    default:  result = 32'h0000_0000;
  endcase
end

// combinational logic
always @(*) begin
  case (alu_func)
    //////////////////////////////////////////////////////////////////////////
    // TODO : Generate check signal
    //////////////////////////////////////////////////////////////////////////
    default:  check = 1'b0;
  endcase
end
endmodule

src/modules/ALU_control.v
// ALU_control.v

/* This unit generates a 4-bit ALU control input (alu_func)
 * based on the 2-bit ALUOp control, funct7, and funct3 field.
 *
 * ALUOp | ALU action | notes  
 * ------|------------|---------------------
 *   00  | add        | for loads and stores
 *   01  | subtract   | for branches
 *   10  | it varies  | for R-types
 *   11  | it varies  | immediate
 *
 * R-type instructions (opcode: 0110011)
 * Name | funct3 | funct7
 * -----------------------
 * add  |  0x0   | 0x00
 * sub  |  0x0   | 0x20
 * xor  |  0x4   | 0x00
 * or   |  0x6   | 0x00
 * and  |  0x7   | 0x00
 * sll  |  0x1   | 0x00
 * srl  |  0x5   | 0x00
 * sra  |  0x5   | 0x20
 * slt  |  0x2   | 0x00
 * sltu |  0x3   | 0x00
 */

`include "defines.v"

module ALU_control(
  input wire [1:0] alu_op,
  input wire [6:0] funct7,
  input wire [2:0] funct3,

  output reg [3:0] alu_func
);

wire [3:0] funct;
assign funct = {funct7[5], funct3};

// combinational logic
always @(*) begin
  case (alu_op)
    2'b00: begin
      ///////////////////////////////////////////////////////////////////////
      // TODO : select operation for loads/stores
      ///////////////////////////////////////////////////////////////////////
    end
    2'b01: begin
      ///////////////////////////////////////////////////////////////////////
      // TODO : select operation for branches
      ///////////////////////////////////////////////////////////////////////
    end
    2'b10: begin                // R-types
      case (funct)
        4'b0_000: alu_func = `OP_ADD;
        4'b1_000: alu_func = `OP_SUB;
        4'b0_100: alu_func = `OP_XOR;
        4'b0_110: alu_func = `OP_OR;
        4'b0_111: alu_func = `OP_AND;
        4'b0_001: alu_func = `OP_SLL;
        4'b0_101: alu_func = `OP_SRL;
        4'b1_101: alu_func = `OP_SRA;
        4'b0_010: alu_func = `OP_SLT;
        4'b0_011: alu_func = `OP_SLTU;
        default:  alu_func = `OP_EEE;  // shoud not fall here 
      endcase
    end
    2'b11: begin
      ///////////////////////////////////////////////////////////////////////
      // TODO : select operation for I-types with immediate
      ///////////////////////////////////////////////////////////////////////
    end
    default: alu_func = `OP_EEE;       // should not fall here
  endcase
end

endmodule

src/modules/register_file.v
// register_file.v
// this models 32, 32-bit registers

module register_file #(
  parameter DATA_WIDTH = 32,
  parameter ADDR_WIDTH = 5
)(
  input clk, 
  input  [ADDR_WIDTH-1:0] rs1, 
  input  [ADDR_WIDTH-1:0] rs2, 
  input  [ADDR_WIDTH-1:0] rd,
  input reg_write, 
  input  [DATA_WIDTH-1:0] write_data,

  output [DATA_WIDTH-1:0] rs1_out,
  output [DATA_WIDTH-1:0] rs2_out
);

  // memory array
  reg [DATA_WIDTH-1:0] reg_array[0:2**ADDR_WIDTH-1];
  initial $readmemh("data/register.mem", reg_array); // change initial register file for fib example

  // update regfile at the falling edge
  always @(negedge clk) begin 
    if (reg_write == 1'b1) reg_array[rd] <= write_data;
    reg_array[0] <= 0; // x0 is always zero in RISC-V
  end

  assign rs1_out = reg_array[rs1];
  assign rs2_out = reg_array[rs2];

endmodule

src/modules/control.v
// control.v

// The main control module takes as input the opcode field of an instruction
// (i.e., instruction[6:0]) and generates a set of control signals.

module control(
  input [6:0] opcode,

  output [1:0] jump,
  output branch,
  output mem_read,
  output mem_to_reg,
  output [1:0] alu_op,
  output mem_write,
  output alu_src,
  output reg_write
);

reg [9:0] controls;

// combinational logic
always @(*) begin
  case (opcode)
    7'b0110011: controls = 10'b00_000_10_001; // R-type
    
    //////////////////////////////////////////////////////////////////////////
    // TODO : Implement signals for other instruction types
    //////////////////////////////////////////////////////////////////////////

    default:    controls = 10'b00_000_00_000;
  endcase
end

assign {jump, branch, mem_read, mem_to_reg, alu_op, mem_write, alu_src, reg_write} = controls;

endmodule

src/modules/adder.v
module adder #(
  parameter DATA_WIDTH = 32
)(
  input [DATA_WIDTH-1:0] in_a,
  input [DATA_WIDTH-1:0] in_b,

  output reg [DATA_WIDTH-1:0] result
);

// combinational logic
always @(*) begin
  result = in_a + in_b;
end

endmodule

src/simple_cpu.v
// simple_cpu.v
// a single-cycle RISC-V microarchitecture (RV32I)

module simple_cpu
#(parameter DATA_WIDTH = 32)(
  input clk,
  input rstn
);


////////////////////////////////////////////////////
// Instruction Fetch (IF)
////////////////////////////////////////////////////


/* m_next_pc_adder */
wire [DATA_WIDTH-1:0] PC_PLUS_4;
reg [DATA_WIDTH-1:0] PC;    // program counter (32 bits)

adder m_next_pc_adder(
  .in_a(PC),
  .in_b(32'h0000_0004),

  .result(PC_PLUS_4)
);

/* pc: update program counter */
wire [DATA_WIDTH-1:0] NEXT_PC;

always @(posedge clk) begin
  if (rstn == 1'b0) PC <= 32'h00000000;
  else PC <= NEXT_PC;
end


/* inst_memory: memory where instruction lies */
localparam NUM_INSTS = 64;

reg [31:0] inst_memory[0:NUM_INSTS-1];
initial $readmemb("data/inst.mem", inst_memory);


/* instruction: current instruction */
wire [DATA_WIDTH-1:0] instruction;
assign instruction = inst_memory[PC[7:2]]; // 64 inst


////////////////////////////////////////////////////
// Instruction Decode (ID)
////////////////////////////////////////////////////


// from register file 
wire [31:0] rs1_out, rs2_out;
wire [31:0] alu_out;

// 5 bits for each (because there exist 32 registers)
wire [4:0] rs1, rs2, rd;

wire [6:0] opcode;
wire [6:0] funct7;
wire [2:0] funct3;

// instruction fields
assign opcode = instruction[6:0];

assign funct7 = instruction[31:25];
assign funct3 = instruction[14:12];

// R type
assign rs1 = instruction[19:15];
assign rs2 = instruction[24:20];
assign rd  = instruction[11:7];

/* m_control: control unit */
wire branch;
wire mem_read;
wire mem_to_reg;
wire [1:0] alu_op;
wire mem_write;
wire alu_src;
wire reg_write;
wire [1:0] jump;

control m_control(
  .opcode(opcode),

  .jump(jump),
  .branch(branch),
  .mem_read(mem_read),
  .mem_to_reg(mem_to_reg),
  .alu_op(alu_op),
  .mem_write(mem_write),
  .alu_src(alu_src),
  .reg_write(reg_write)
);

/* m_register_file: register file */
wire [DATA_WIDTH-1:0] write_data; 
wire [DATA_WIDTH-1:0] read_data;

register_file m_register_file(
  .clk(clk),
  .rs1(rs1),
  .rs2(rs2),
  .rd(rd),
  .reg_write(reg_write),
  .write_data(write_data),
  
  .rs1_out(rs1_out),
  .rs2_out(rs2_out)
);

///////////////////////////////////////////////////////////////////////////////
// TODO : Immediate Generator
//////////////////////////////////////////////////////////////////////////////


////////////////////////////////////////////////////
// Execute (EX) 
////////////////////////////////////////////////////


/* m_ALU_control: ALU control unit */
wire [3:0] alu_func;

ALU_control m_ALU_control(
  .alu_op(alu_op), 
  .funct7(funct7),
  .funct3(funct3),

  .alu_func(alu_func)
);

wire [31:0] alu_in2;

///////////////////////////////////////////////////////////////////////////////
// TODO : Need a fix
//////////////////////////////////////////////////////////////////////////////
assign alu_in2 = rs2_out;

//////////////////////////////////////////////////////////////////////////////

/* m_ALU: ALU */
wire [31:0] alu_in1;
wire alu_check;

assign alu_in1 = rs1_out;

ALU m_ALU(
  .in_a(alu_in1), 
  .in_b(alu_in2), // is input with reg allowed?? 
  .alu_func(alu_func),

  // output
  .result(alu_out),
  .check(alu_check)
);


////////////////////////////////////////////////////
// Memory (MEM) 
////////////////////////////////////////////////////

/* m_branch_control: generate taken for branch instruction */
wire taken;

branch_control m_branch_control(
  .branch(branch),
  .check(alu_check),

  .taken(taken)
);

///////////////////////////////////////////////////////////////////////////////
// TODO : Currently, NEXT_PC is always PC_PLUS_4. Using adders and muxes & 
// control signals, compute & assign the correct NEXT_PC.
//////////////////////////////////////////////////////////////////////////////
assign NEXT_PC = PC_PLUS_4;


///////////////////////////////////////////////////////////////////////////////
// TODO : Feed the appropriate inputs to the data memory
//////////////////////////////////////////////////////////////////////////////
/* m_data_memory: data memory */
data_memory m_data_memory(
  .clk(clk),
  .mem_write(mem_write),
  .mem_read(mem_read),
  .maskmode(2'b00),
  .sext(1'b0),
  .address(32'b0),
  .write_data(32'b0),

  .read_data(read_data)
);
//////////////////////////////////////////////////////////////////////////////


////////////////////////////////////////////////////
// Write Back (WB) 
////////////////////////////////////////////////////

///////////////////////////////////////////////////////////////////////////////
// TODO : Need a fix
//////////////////////////////////////////////////////////////////////////////
assign write_data = alu_out;

//////////////////////////////////////////////////////////////////////////////
endmodule

src/riscv_tb.v
`timescale 1 ns/10 ps

module riscv_tb;

reg clk, rstn;
wire [31:0] inst;

integer i;

initial begin
  clk  = 1'b0;
  rstn = 1'b0;
  $display($time, " ** Start Simulation **");
  $display($time, " Instruction Memory ");
  for (i=0;i<64;i=i+1) $display($time, " INST[%2d]: %b", i, my_cpu.inst_memory[i]);
  $monitor($time, " [PC] pc : %d", my_cpu.PC);
  #60 rstn = 1'b1;
  #3760; // for Fibonacci example
  rstn = 1'b0;
  $display($time, " ** End Simulation **");
  $display($time, " REGISTER FILE");
  for (i=0;i<32;i=i+1) $display($time, " Reg[%d]: %d (%b)", i, $signed(my_cpu.m_register_file.reg_array[i]), my_cpu.m_register_file.reg_array[i]);
  $display($time, " DATA MEMORY");
  for (i=0;i<128;i=i+1) $display($time, " Mem[%d]: %d (%b)", i, $signed(my_cpu.m_data_memory.mem_array[i]), my_cpu.m_data_memory.mem_array[i]);
  $finish;
end

always begin
  #20 clk = ~clk;
end

// dump the state of the design
// VCD (Value Change Dump) is a standard dump format defined in Verilog.
initial begin
  $dumpfile("sim.vcd");
  $dumpvars(0, riscv_tb);
end

simple_cpu my_cpu(.clk(clk), .rstn(rstn));

endmodule

sim.vcd
$date
	Sat Apr  2 03:12:12 2022
$end
$version
	Icarus Verilog
$end
$timescale
	10ps
$end
$scope module riscv_tb $end
$var reg 1 ! clk $end
$var reg 1 " rstn $end
$var integer 32 # i [31:0] $end
$scope module my_cpu $end
$var wire 32 $ NEXT_PC [31:0] $end
$var wire 32 % alu_in1 [31:0] $end
$var wire 32 & alu_in2 [31:0] $end
$var wire 1 ! clk $end
$var wire 32 ' instruction [31:0] $end
$var wire 1 " rstn $end
$var wire 32 ( write_data [31:0] $end
$var wire 1 ) taken $end
$var wire 32 * rs2_out [31:0] $end
$var wire 5 + rs2 [4:0] $end
$var wire 32 , rs1_out [31:0] $end
$var wire 5 - rs1 [4:0] $end
$var wire 1 . reg_write $end
$var wire 32 / read_data [31:0] $end
$var wire 5 0 rd [4:0] $end
$var wire 7 1 opcode [6:0] $end
$var wire 1 2 mem_write $end
$var wire 1 3 mem_to_reg $end
$var wire 1 4 mem_read $end
$var wire 2 5 jump [1:0] $end
$var wire 7 6 funct7 [6:0] $end
$var wire 3 7 funct3 [2:0] $end
$var wire 1 8 branch $end
$var wire 1 9 alu_src $end
$var wire 32 : alu_out [31:0] $end
$var wire 2 ; alu_op [1:0] $end
$var wire 4 < alu_func [3:0] $end
$var wire 1 = alu_check $end
$var wire 32 > PC_PLUS_4 [31:0] $end
$var reg 32 ? PC [31:0] $end
$scope module m_ALU $end
$var wire 32 @ in_a [31:0] $end
$var wire 32 A in_b [31:0] $end
$var wire 4 B alu_func [3:0] $end
$var reg 1 = check $end
$var reg 32 C result [31:0] $end
$upscope $end
$scope module m_ALU_control $end
$var wire 3 D funct3 [2:0] $end
$var wire 7 E funct7 [6:0] $end
$var wire 4 F funct [3:0] $end
$var wire 2 G alu_op [1:0] $end
$var reg 4 H alu_func [3:0] $end
$upscope $end
$scope module m_branch_control $end
$var wire 1 = check $end
$var wire 1 8 branch $end
$var reg 1 ) taken $end
$upscope $end
$scope module m_control $end
$var wire 7 I opcode [6:0] $end
$var wire 1 . reg_write $end
$var wire 1 2 mem_write $end
$var wire 1 3 mem_to_reg $end
$var wire 1 4 mem_read $end
$var wire 2 J jump [1:0] $end
$var wire 1 8 branch $end
$var wire 1 9 alu_src $end
$var wire 2 K alu_op [1:0] $end
$var reg 10 L controls [9:0] $end
$upscope $end
$scope module m_data_memory $end
$var wire 32 M address [31:0] $end
$var wire 1 ! clk $end
$var wire 2 N maskmode [1:0] $end
$var wire 1 4 mem_read $end
$var wire 1 2 mem_write $end
$var wire 1 O sext $end
$var wire 32 P write_data [31:0] $end
$var wire 8 Q address_internal [7:0] $end
$var reg 32 R read_data [31:0] $end
$upscope $end
$scope module m_next_pc_adder $end
$var wire 32 S in_a [31:0] $end
$var wire 32 T in_b [31:0] $end
$var reg 32 U result [31:0] $end
$upscope $end
$scope module m_register_file $end
$var wire 1 ! clk $end
$var wire 5 V rd [4:0] $end
$var wire 1 . reg_write $end
$var wire 5 W rs1 [4:0] $end
$var wire 32 X rs1_out [31:0] $end
$var wire 5 Y rs2 [4:0] $end
$var wire 32 Z rs2_out [31:0] $end
$var wire 32 [ write_data [31:0] $end
$upscope $end
$upscope $end
$upscope $end
$enddefinitions $end
#0
$dumpvars
bx [
bx Z
bx Y
bx X
bx W
bx V
bx U
b100 T
bx S
bx R
b0 Q
b0 P
0O
b0 N
b0 M
bx L
bx K
bx J
bx I
bx H
bx G
bx F
bx E
bx D
bx C
bx B
bx A
bx @
bx ?
bx >
x=
bx <
bx ;
bx :
x9
x8
bx 7
bx 6
bx 5
x4
x3
x2
bx 1
bx 0
bx /
x.
bx -
bx ,
bx +
bx *
x)
bx (
bx '
bx &
bx %
bx $
b1000000 #
0"
0!
$end
#2000
b0 /
b0 R
b0 5
b0 J
08
04
03
b0 ;
b0 G
b0 K
02
09
0.
0=
b0 L
b1111 <
b1111 B
b1111 H
b0 (
b0 [
b0 :
b0 C
b10011 1
b10011 I
b1111111 6
b1111111 E
b1000 F
b0 7
b0 D
b100000000 %
b100000000 @
b100000000 ,
b100000000 X
b10 -
b10 W
b0 &
b0 A
b0 *
b0 Z
b0 +
b0 Y
b10 0
b10 V
b11111110000000010000000100010011 '
b100 $
b100 >
b100 U
b0 ?
b0 S
1!
#4000
0!
#6000
b100011 1
b100011 I
b0 6
b0 E
b10 F
b10 7
b10 D
b1000 +
b1000 Y
b11100 0
b11100 V
b100000010010111000100011 '
b1000 $
b1000 >
b1000 U
b100 ?
b100 S
1!
1"
#8000
0!
#10000
b11011000 &
b11011000 A
b11011000 *
b11011000 Z
b1 +
b1 Y
b11000 0
b11000 V
b100010010110000100011 '
b1100 $
b1100 >
b1100 U
b1000 ?
b1000 S
1!
#12000
0!
#14000
b10011 1
b10011 I
b0 F
b0 7
b0 D
b0 &
b0 A
b0 *
b0 Z
b10000 +
b10000 Y
b1000 0
b1000 V
b1000000010000010000010011 '
b10000 $
b10000 >
b10000 U
b1100 ?
b1100 S
1!
#16000
0!
#18000
b100011 1
b100011 I
b1111111 6
b1111111 E
b1010 F
b10 7
b10 D
b0 %
b0 @
b0 ,
b0 X
b1000 -
b1000 W
b10 &
b10 A
b10 *
b10 Z
b1010 +
b1010 Y
b11100 0
b11100 V
b11111110101001000010111000100011 '
b10100 $
b10100 >
b10100 U
b10000 ?
b10000 S
1!
#20000
0!
#22000
b10011 1
b10011 I
b0 6
b0 E
b0 F
b0 7
b0 D
b0 &
b0 A
b0 *
b0 Z
b0 +
b0 Y
b1010 0
b1010 V
b1000000010100010011 '
b11000 $
b11000 >
b11000 U
b10100 ?
b10100 S
1!
#24000
0!
#26000
b1000 F
b1111111 6
b1111111 E
b10 %
b10 @
b10 ,
b10 X
b1010 -
b1010 W
b11100 +
b11100 Y
b11111111110001010000010100010011 '
b11100 $
b11100 >
b11100 U
b11000 ?
b11000 S
1!
#28000
0!
#30000
b11 1
b11 I
b0 6
b0 E
b10 F
b10 7
b10 D
b0 +
b0 Y
b1010010010100000011 '
b100000 $
b100000 >
b100000 U
b11100 ?
b11100 S
1!
#32000
0!
#34000
b10011 1
b10011 I
b0 F
b0 7
b0 D
b0 %
b0 @
b0 ,
b0 X
b0 -
b0 W
b1011 0
b1011 V
b10110010011 '
b100100 $
b100100 >
b100100 U
b100000 ?
b100000 S
1!
#36000
0!
#38000
b1100011 1
b1100011 I
b10 %
b10 @
b10 ,
b10 X
b1010 -
b1010 W
b1010 &
b1010 A
b1010 *
b1010 Z
b1011 +
b1011 Y
b1100 0
b1100 V
b101101010000011001100011 '
b101000 $
b101000 >
b101000 U
b100100 ?
b100100 S
1!
#40000
0!
#42000
b10011 1
b10011 I
b0 %
b0 @
b0 ,
b0 X
b0 -
b0 W
b0 &
b0 A
b0 *
b0 Z
b0 +
b0 Y
b1010 0
b1010 V
b10100010011 '
b101100 $
b101100 >
b101100 U
b101000 ?
b101000 S
1!
#44000
0!
#46000
b1101111 1
b1101111 I
b1000 +
b1000 Y
b0 0
b0 V
b100000000000000001101111 '
b110000 $
b110000 >
b110000 U
b101100 ?
b101100 S
1!
#48000
0!
#50000
b10011 1
b10011 I
b11011000 &
b11011000 A
b11011000 *
b11011000 Z
b1 +
b1 Y
b1010 0
b1010 V
b100000000010100010011 '
b110100 $
b110100 >
b110100 U
b110000 ?
b110000 S
1!
#52000
0!
#54000
b0 &
b0 A
b0 *
b0 Z
b0 +
b0 Y
b0 0
b0 V
b10011 '
b111000 $
b111000 >
b111000 U
b110100 ?
b110100 S
1!
#56000
0!
#58000
b1100011 1
b1100011 I
b10 %
b10 @
b10 ,
b10 X
b1010 -
b1010 W
b10000 0
b10000 V
b1010000100001100011 '
b111100 $
b111100 >
b111100 U
b111000 ?
b111000 S
1!
#60000
0!
#62000
b10011 1
b10011 I
b0 %
b0 @
b0 ,
b0 X
b0 -
b0 W
b1010 0
b1010 V
b10100010011 '
b1000000 $
b1000000 >
b1000000 U
b111100 ?
b111100 S
1!
#64000
0!
#66000
b1101111 1
b1101111 I
b100 6
b100 E
b1000 +
b1000 Y
b0 0
b0 V
b1000100000000000000001101111 '
b1000100 $
b1000100 >
b1000100 U
b1000000 ?
b1000000 S
1!
#68000
0!
#70000
b100 +
b100 Y
b1000010000000000000001101111 '
b1001000 $
b1001000 >
b1001000 U
b1000100 ?
b1000100 S
1!
#72000
0!
#74000
b10011 1
b10011 I
b0 6
b0 E
b1000 -
b1000 W
b0 +
b0 Y
b1010 0
b1010 V
b1000000010100010011 '
b1001100 $
b1001100 >
b1001100 U
b1001000 ?
b1001000 S
1!
#76000
0!
#78000
b1000 F
b1111111 6
b1111111 E
b10 %
b10 @
b10 ,
b10 X
b1010 -
b1010 W
b11100 +
b11100 Y
b11111111110001010000010100010011 '
b1010000 $
b1010000 >
b1010000 U
b1001100 ?
b1001100 S
1!
#80000
0!
#82000
b11 1
b11 I
b0 6
b0 E
b10 F
b10 7
b10 D
b0 +
b0 Y
b1010010010100000011 '
b1010100 $
b1010100 >
b1010100 U
b1010000 ?
b1010000 S
1!
#84000
0!
#86000
b10011 1
b10011 I
b0 F
b0 7
b0 D
b0 %
b0 @
b0 ,
b0 X
b0 -
b0 W
b11011000 &
b11011000 A
b11011000 *
b11011000 Z
b1 +
b1 Y
b1011 0
b1011 V
b100000000010110010011 '
b1011000 $
b1011000 >
b1011000 U
b1010100 ?
b1010100 S
1!
#88000
0!
#90000
b1100011 1
b1100011 I
b10 %
b10 @
b10 ,
b10 X
b1010 -
b1010 W
b1010 &
b1010 A
b1010 *
b1010 Z
b1011 +
b1011 Y
b1100 0
b1100 V
b101101010000011001100011 '
b1011100 $
b1011100 >
b1011100 U
b1011000 ?
b1011000 S
1!
#92000
0!
#94000
b10011 1
b10011 I
b0 %
b0 @
b0 ,
b0 X
b0 -
b0 W
b0 &
b0 A
b0 *
b0 Z
b0 +
b0 Y
b1010 0
b1010 V
b10100010011 '
b1100000 $
b1100000 >
b1100000 U
b1011100 ?
b1011100 S
1!
#96000
0!
#98000
b1101111 1
b1101111 I
b1000 +
b1000 Y
b0 0
b0 V
b100000000000000001101111 '
b1100100 $
b1100100 >
b1100100 U
b1100000 ?
b1100000 S
1!
#100000
0!
#102000
b10011 1
b10011 I
b11011000 &
b11011000 A
b11011000 *
b11011000 Z
b1 +
b1 Y
b1010 0
b1010 V
b100000000010100010011 '
b1101000 $
b1101000 >
b1101000 U
b1100100 ?
b1100100 S
1!
#104000
0!
#106000
b0 &
b0 A
b0 *
b0 Z
b0 +
b0 Y
b0 0
b0 V
b10011 '
b1101100 $
b1101100 >
b1101100 U
b1101000 ?
b1101000 S
1!
#108000
0!
#110000
b1100011 1
b1100011 I
b10 %
b10 @
b10 ,
b10 X
b1010 -
b1010 W
b10000 0
b10000 V
b1010000100001100011 '
b1110000 $
b1110000 >
b1110000 U
b1101100 ?
b1101100 S
1!
#112000
0!
#114000
b10011 1
b10011 I
b0 %
b0 @
b0 ,
b0 X
b0 -
b0 W
b11011000 &
b11011000 A
b11011000 *
b11011000 Z
b1 +
b1 Y
b1010 0
b1010 V
b100000000010100010011 '
b1110100 $
b1110100 >
b1110100 U
b1110000 ?
b1110000 S
1!
#116000
0!
#118000
b1101111 1
b1101111 I
b10 6
b10 E
b0 &
b0 A
b0 *
b0 Z
b10100 +
b10100 Y
b0 0
b0 V
b101010000000000000001101111 '
b1111000 $
b1111000 >
b1111000 U
b1110100 ?
b1110100 S
1!
#120000
0!
#122000
b10000 +
b10000 Y
b101000000000000000001101111 '
b1111100 $
b1111100 >
b1111100 U
b1111000 ?
b1111000 S
1!
#124000
0!
#126000
b10011 1
b10011 I
b0 6
b0 E
b1000 -
b1000 W
b0 +
b0 Y
b1010 0
b1010 V
b1000000010100010011 '
b10000000 $
b10000000 >
b10000000 U
b1111100 ?
b1111100 S
1!
#128000
0!
#130000
b1000 F
b1111111 6
b1111111 E
b10 %
b10 @
b10 ,
b10 X
b1010 -
b1010 W
b11100 +
b11100 Y
b11111111110001010000010100010011 '
b10000100 $
b10000100 >
b10000100 U
b10000000 ?
b10000000 S
1!
#132000
0!
#134000
b11 1
b11 I
b0 6
b0 E
b10 F
b10 7
b10 D
b0 +
b0 Y
b1010010010100000011 '
b10001000 $
b10001000 >
b10001000 U
b10000100 ?
b10000100 S
1!
#136000
0!
#138000
b10011 1
b10011 I
b0 F
b0 7
b0 D
b0 %
b0 @
b0 ,
b0 X
b0 -
b0 W
b11011000 &
b11011000 A
b11011000 *
b11011000 Z
b1 +
b1 Y
b1011 0
b1011 V
b100000000010110010011 '
b10001100 $
b10001100 >
b10001100 U
b10001000 ?
b10001000 S
1!
#140000
0!
#142000
b11111111111111111111111111111000 (
b11111111111111111111111111111000 [
b11111111111111111111111111111000 :
b11111111111111111111111111111000 C
b1 <
b1 B
b1 H
b10 ;
b10 G
b10 K
1.
b10001 L
b1000 F
b110011 1
b110011 I
b100000 6
b100000 E
b10 %
b10 @
b10 ,
b10 X
b1010 -
b1010 W
b1010 &
b1010 A
b1010 *
b1010 Z
b1011 +
b1011 Y
b1010 0
b1010 V
b1000000101101010000010100110011 '
b10010000 $
b10010000 >
b10010000 U
b10001100 ?
b10001100 S
1!
#144000
b11111111111111111111111111101110 (
b11111111111111111111111111101110 [
b11111111111111111111111111101110 :
b11111111111111111111111111101110 C
b11111111111111111111111111111000 %
b11111111111111111111111111111000 @
b11111111111111111111111111111000 ,
b11111111111111111111111111111000 X
0!
#146000
b0 ;
b0 G
b0 K
0.
b0 L
b1111 <
b1111 B
b1111 H
b0 (
b0 [
b0 :
b0 C
b1101111 1
b1101111 I
b1111011 6
b1111011 E
b1111 F
b111 7
b111 D
b0 %
b0 @
b0 ,
b0 X
b11111 -
b11111 W
b0 &
b0 A
b0 *
b0 Z
b10001 +
b10001 Y
b1 0
b1 V
b11110111000111111111000011101111 '
b10010100 $
b10010100 >
b10010100 U
b10010000 ?
b10010000 S
1!
#148000
0!
#150000
b10011 1
b10011 I
b1111111 6
b1111111 E
b1000 F
b0 7
b0 D
b100000000 %
b100000000 @
b100000000 ,
b100000000 X
b10 -
b10 W
b10000 +
b10000 Y
b10 0
b10 V
b11111111000000010000000100010011 '
b10011000 $
b10011000 >
b10011000 U
b10010100 ?
b10010100 S
1!
#152000
0!
#154000
b100011 1
b100011 I
b0 6
b0 E
b10 F
b10 7
b10 D
b11111111111111111111111111111000 &
b11111111111111111111111111111000 A
b11111111111111111111111111111000 *
b11111111111111111111111111111000 Z
b1010 +
b1010 Y
b0 0
b0 V
b101000010010000000100011 '
b10011100 $
b10011100 >
b10011100 U
b10011000 ?
b10011000 S
1!
#156000
0!
#158000
b10011 1
b10011 I
b0 F
b0 7
b0 D
b0 %
b0 @
b0 ,
b0 X
b1000 -
b1000 W
b0 &
b0 A
b0 *
b0 Z
b0 +
b0 Y
b1010 0
b1010 V
b1000000010100010011 '
b10100000 $
b10100000 >
b10100000 U
b10011100 ?
b10011100 S
1!
#160000
0!
#162000
b1000 F
b1111111 6
b1111111 E
b11111111111111111111111111111000 %
b11111111111111111111111111111000 @
b11111111111111111111111111111000 ,
b11111111111111111111111111111000 X
b1010 -
b1010 W
b11100 +
b11100 Y
b11111111110001010000010100010011 '
b10100100 $
b10100100 >
b10100100 U
b10100000 ?
b10100000 S
1!
#164000
0!
#166000
b11 1
b11 I
b0 6
b0 E
b10 F
b10 7
b10 D
b0 +
b0 Y
b1010010010100000011 '
b10101000 $
b10101000 >
b10101000 U
b10100100 ?
b10100100 S
1!
#168000
0!
#170000
b10011 1
b10011 I
b0 F
b0 7
b0 D
b0 %
b0 @
b0 ,
b0 X
b0 -
b0 W
b100000000 &
b100000000 A
b100000000 *
b100000000 Z
b10 +
b10 Y
b1011 0
b1011 V
b1000000000010110010011 '
b10101100 $
b10101100 >
b10101100 U
b10101000 ?
b10101000 S
1!
#172000
0!
#174000
b11111111111111111111111111101110 (
b11111111111111111111111111101110 [
b11111111111111111111111111101110 :
b11111111111111111111111111101110 C
b1 <
b1 B
b1 H
b10 ;
b10 G
b10 K
1.
b10001 L
b1000 F
b110011 1
b110011 I
b100000 6
b100000 E
b11111111111111111111111111111000 %
b11111111111111111111111111111000 @
b11111111111111111111111111111000 ,
b11111111111111111111111111111000 X
b1010 -
b1010 W
b1010 &
b1010 A
b1010 *
b1010 Z
b1011 +
b1011 Y
b1010 0
b1010 V
b1000000101101010000010100110011 '
b10110000 $
b10110000 >
b10110000 U
b10101100 ?
b10101100 S
1!
#176000
b11111111111111111111111111100100 (
b11111111111111111111111111100100 [
b11111111111111111111111111100100 :
b11111111111111111111111111100100 C
b11111111111111111111111111101110 %
b11111111111111111111111111101110 @
b11111111111111111111111111101110 ,
b11111111111111111111111111101110 X
0!
#178000
b0 ;
b0 G
b0 K
0.
b0 L
b1111 <
b1111 B
b1111 H
b0 (
b0 [
b0 :
b0 C
b1101111 1
b1101111 I
b1111010 6
b1111010 E
b1111 F
b111 7
b111 D
b0 %
b0 @
b0 ,
b0 X
b11111 -
b11111 W
b0 &
b0 A
b0 *
b0 Z
b10001 +
b10001 Y
b1 0
b1 V
b11110101000111111111000011101111 '
b10110100 $
b10110100 >
b10110100 U
b10110000 ?
b10110000 S
1!
#180000
0!
